<?xml version="1.0" encoding="UTF-8"?>
<TelemFFB>
	<defaults>
		<Grouping>Engine</Grouping>
		<name>afterburner_effect_intensity</name>
		<displayname>Afterburner</displayname>
		<value Craft="JetAircraft">0.2</value>
		<datatype>float</datatype>
		<DCS>true</DCS>
		<MSFS>true</MSFS>
		<joystick>true</joystick>
	</defaults>
	<defaults>
		<Grouping>Basic</Grouping>
		<name>aileron_area</name>
		<displayname>Aileron Area</displayname>
		<value Craft="PropellerAircraft">0.7</value>
		<value Craft="TurbopropAircraft">1.0</value>
		<datatype>float</datatype>
		<joystick>true</joystick>
		<info>square meters</info>
	</defaults>
	<defaults>
		<Grouping>Basic</Grouping>
		<name>aileron_gain</name>
		<displayname>Aileron Gain</displayname>
		<value Craft="Default">0.2</value>
		<value Craft="TurbopropAircraft">0.2</value>
		<value Craft="GliderAircraft">0.1</value>
		<datatype>float</datatype>
		<MSFS>true</MSFS>
		<joystick>true</joystick>
	</defaults>
	<defaults>
		<Grouping>SpringCenter</Grouping>
		<name>aileron_spring_gain</name>
		<displayname>Aileron Spring Gain</displayname>
		<value Craft="GliderAircraft">0.25</value>
		<value Craft="TurbopropAircraft">0.5</value>
		<datatype>float</datatype>
		<MSFS>true</MSFS>
		<joystick>true</joystick>
	</defaults>
	<defaults>
		<Grouping>FlyByWire</Grouping>
		<name>aircraft_is_fbw</name>
		<displayname>Enable FlyByWire (FBW)</displayname>
		<value>false</value>
		<datatype>bool</datatype>
		<MSFS>true</MSFS>
		<joystick>true</joystick>
		<pedals>true</pedals>
	</defaults>
	<defaults>
		<Grouping>SpringCenter</Grouping>
		<name>aircraft_is_spring_centered</name>
		<displayname>Enable Spring Centering</displayname>
		<value Craft="GliderAircraft">false</value>
		<value Craft="TurbopropAircraft">true</value>
		<datatype>bool</datatype>
		<MSFS>true</MSFS>
		<joystick>true</joystick>
		<pedals>true</pedals>
	</defaults>
	<defaults>
		<Grouping>Buffeting</Grouping>
		<name>aoa_effect_enabled</name>
		<displayname>Enable Buffeting</displayname>
		<value>true</value>
		<datatype>bool</datatype>
		<DCS>true</DCS>
		<MSFS>true</MSFS>
		<joystick>true</joystick>
		<info>enable or disable the dynamic AoA based forces effect</info>
	</defaults>
	<defaults>
		<Grouping>AoA Reduction</Grouping>
		<name>aoa_reduction_effect_enabled</name>
		<displayname>Enable AoA Reduction</displayname>
		<value>false</value>
		<datatype>bool</datatype>
		<DCS>true</DCS>
		<MSFS>true</MSFS>
		<joystick>true</joystick>
	</defaults>
	<defaults>
		<Grouping>AoA Reduction</Grouping>
		<name>aoa_reduction_max_force</name>
		<displayname>AoA Reduction Max Force</displayname>
		<value>1.0</value>
		<datatype>float</datatype>
		<DCS>true</DCS>
		<MSFS>true</MSFS>
		<joystick>true</joystick>
		<info>Max 'constant' force to apply</info>
	</defaults>
	<defaults>
		<Grouping>Autopilot</Grouping>
		<name>ap_following</name>
		<displayname>Enable Autopilot Following</displayname>
		<value>true</value>
		<datatype>bool</datatype>
		<MSFS>true</MSFS>
		<joystick>true</joystick>
	</defaults>
	<defaults>
		<Grouping>Buffeting</Grouping>
		<name>buffet_aoa</name>
		<displayname>Buffet Onset Aoa</displayname>
		<value>10</value>
		<datatype>int</datatype>
		<DCS>true</DCS>
		<joystick>true</joystick>
		<info>AoA when buffeting starts</info>
	</defaults>
	<defaults>
		<Grouping>Buffeting</Grouping>
		<name>buffeting_intensity</name>
		<displayname>Buffeting Intensity</displayname>
		<value>0.2</value>
		<datatype>float</datatype>
		<DCS>true</DCS>
		<joystick>true</joystick>
		<info>peak AoA buffeting intensity  0 to disable</info>
		</defaults>
	<defaults>
		<Grouping>Movement</Grouping>
		<name>canopy_motion_intensity</name>
		<displayname>Canopy Motion</displayname>
		<value>0.12</value>
		<datatype>float</datatype>
		<DCS>true</DCS>
		<joystick>true</joystick>
		<info>peak vibration intensity when canopy is moving, 0 to disable</info>
	</defaults>
	<defaults>
		<Grouping>Basic</Grouping>
		<name>center_spring_on_pause</name>
		<displayname>Center on Pause/Slew</displayname>
		<value>false</value>
		<datatype>bool</datatype>
		<MSFS>true</MSFS>
		<joystick>true</joystick>
		<pedals>true</pedals>
		</defaults>
	<defaults>
		<Grouping>Weapons</Grouping>
		<name>cm_vibration_intensity</name>
		<displayname>Countermeasure Release</displayname>
		<value>0.2</value>
		<datatype>float</datatype>
		<DCS>true</DCS>
		<joystick>true</joystick>
		<info>peak intensity for countermeasure release effect, 0 to disable</info>
	</defaults>
	<defaults>
		<Grouping>SpringCenter</Grouping>
		<name>collective_ap_spring_gain</name>
		<displayname>Collective AP Spring Gain</displayname>
		<value Craft="Helicopter">1.0</value>
		<value Craft="HPGHelicopter">1.0</value>
		<datatype>float</datatype>
		<MSFS>true</MSFS>
		<collective>true</collective>
	</defaults>
	<defaults>
		<Grouping>SpringCenter</Grouping>
		<name>collective_dampening_gain</name>
		<displayname>Collective Dampening Gain</displayname>
		<value Craft="Helicopter">0.4</value>
		<value Craft="HPGHelicopter">0.4</value>
		<datatype>float</datatype>
		<DCS>true</DCS>
		<MSFS>true</MSFS>
		<collective>true</collective>
	</defaults>
	<defaults>
		<Grouping>AoA Reduction</Grouping>
		<name>critical_aoa_max</name>
		<displayname>Critical AoA Max Speed</displayname>
		<value>25</value>
		<unit>m/s</unit>
		<datatype>int</datatype>
		<DCS>true</DCS>
		<MSFS>true</MSFS>
		<joystick>true</joystick>
		<info>AoA at which applied force maxes out</info>
	</defaults>
	<defaults>
		<Grouping>AoA Reduction</Grouping>
		<name>critical_aoa_start</name>
		<displayname>Critical AoA Start Speed</displayname>
		<value>22</value>
		<unit>m/s</unit>
		<datatype>int</datatype>
		<DCS>true</DCS>
		<MSFS>true</MSFS>
		<joystick>true</joystick>
		<info>AoA at which to begin applying force</info>
	</defaults>
	<defaults>
		<Grouping>Basic</Grouping>
		<name>cyclic_spring_gain</name>
		<displayname>Cyclic Spring Gain</displayname>
		<value Craft="Helicopter">1.0</value>
		<value Craft="HPGHelicopter">0.75</value>
		<datatype>float</datatype>
		<MSFS>true</MSFS>
		<joystick>true</joystick>
	</defaults>
	<defaults>
		<Grouping>Weapons</Grouping>
		<name>damage_effect_enabled</name>
		<displayname>Enable Damage Effect</displayname>
		<value>false</value>
		<datatype>bool</datatype>
		<DCS>true</DCS>
		<joystick>true</joystick>
		<pedals>true</pedals>
	</defaults>
	<defaults>
		<Grouping>Weapons</Grouping>
		<name>damage_effect_intensity</name>
		<displayname>Damage Effect</displayname>
		<value>0.4</value>
		<datatype>float</datatype>
		<DCS>true</DCS>
		<IL2>true</IL2>
		<joystick>true</joystick>
		<pedals>true</pedals>
		<info>peak vibration intensity when flaps are moving, 0 to disable</info>
	</defaults>
	<defaults>
		<Grouping>System</Grouping>
		<name>dcs_enabled</name>
		<displayname>Enable DCS</displayname>
		<value>true</value>
		<datatype>bool</datatype>
		<Global>true</Global>
		<joystick>true</joystick>
		<pedals>true</pedals>
		<info>can also run app with '-s DCS' argument</info>
	</defaults>
	<defaults>
		<Grouping>G Force</Grouping>
		<name>deceleration_effect_enable</name>
		<displayname>Enable Decelleration Effect</displayname>
		<value>true</value>
		<datatype>bool</datatype>
		<DCS>true</DCS>
		<IL2>true</IL2>
		<joystick>true</joystick>
		<info>Deceleration effect pulls the stick forward when on the ground and decelerating</info>
	</defaults>
	<defaults>
		<Grouping>G Force</Grouping>
		<name>deceleration_max_force</name>
		<displayname>Decelleration Max Force</displayname>
		<value>0.6</value>
		<datatype>float</datatype>
		<DCS>true</DCS>
		<IL2>true</IL2>
		<joystick>true</joystick>
		<info>Deceleration effect pulls the stick forward when on the ground and decelerating</info>
		</defaults>
	<defaults>
		<Grouping>Basic</Grouping>
		<name>elevator_area</name>
		<displayname>Elevator Area</displayname>
		<value Craft="PropellerAircraft">1.2</value>
		<value Craft="TurbopropAircraft">2.2</value>
		<datatype>float</datatype>
		<joystick>true</joystick>
		<info>square meters</info>
	</defaults>
	<defaults>
		<Grouping>Basic</Grouping>
		<name>elevator_droop_moment</name>
		<displayname>Elevator Droop Moment</displayname>
		<value>0.1</value>
		<datatype>float</datatype>
		<MSFS>true</MSFS>
		<joystick>true</joystick>
	</defaults>
	<defaults>
		<Grouping>Basic</Grouping>
		<name>elevator_gain</name>
		<displayname>Elevator Gain</displayname>
		<value Craft="Default">0.2</value>
		<value Craft="PropellerAircraft">0.3</value>
		<value Craft="TurbopropAircraft">0.2</value>
		<value Craft="GliderAircraft">0.2</value>
		<datatype>float</datatype>
		<MSFS>true</MSFS>
		<joystick>true</joystick>
	</defaults>
	<defaults>
		<Grouping>Prop</Grouping>
		<name>elevator_prop_flow_ratio</name>
		<displayname>Elevator Prop Flow</displayname>
		<value Craft="PropellerAircraft">0.2</value>
		<value Craft="TurbopropAircraft">0.2</value>
		<datatype>float</datatype>
		<MSFS>true</MSFS>
		<joystick>true</joystick>
	</defaults>
	<defaults>
		<Grouping>SpringCenter</Grouping>
		<name>elevator_spring_gain</name>
		<displayname>Elevator Spring Gain</displayname>
		<value Craft="GliderAircraft">0.25</value>
		<value Craft="TurbopropAircraft">0.5</value>
		<datatype>float</datatype>
		<MSFS>true</MSFS>
		<joystick>true</joystick>
	</defaults>
	<defaults>
		<Grouping>Engine</Grouping>
		<name>engine_rumble</name>
		<displayname>Engine Rumble</displayname>
		<value>true</value>
		<datatype>bool</datatype>
		<Global>true</Global>
		<joystick>true</joystick>
		<pedals>true</pedals>
		<collective>true</collective>
		</defaults>
	<defaults>
		<Grouping>Engine</Grouping>
		<name>engine_rumble_highrpm</name>
		<displayname>Engine Rumble High RPM</displayname>
		<value Craft="PropellerAircraft">2800</value>
		<value Craft="TurbopropAircraft">2800</value>
		<datatype>float</datatype>
		<Global>true</Global>
		<joystick>true</joystick>
		<pedals>true</pedals>
		<collective>true</collective>
		<info>high RPM threshold for high rpm intensity setting</info>
	</defaults>
	<defaults>
		<Grouping>Engine</Grouping>
		<name>engine_rumble_highrpm_intensity</name>
		<displayname>Engine Rumble High Intensity</displayname>
		<value Craft="PropellerAircraft">0.03</value>
		<value Craft="TurbopropAircraft">0.03</value>
		<datatype>float</datatype>
		<Global>true</Global>
		<joystick>true</joystick>
		<pedals>true</pedals>
		<collective>true</collective>
		<info>peak intensity of engine rumble at high RPM threshold</info>
	</defaults>
	<defaults>
		<Grouping>Engine</Grouping>
		<name>engine_rumble_lowrpm</name>
		<displayname>Engine Rumble Low RPM</displayname>
		<value Craft="PropellerAircraft">650</value>
		<value Craft="TurbopropAircraft">650</value>
		<datatype>float</datatype>
		<Global>true</Global>
		<joystick>true</joystick>
		<pedals>true</pedals>
		<collective>true</collective>
		<info>low RPM threshold for low rpm intensity setting</info>
	</defaults>
	<defaults>
		<Grouping>Engine</Grouping>
		<name>engine_rumble_lowrpm_intensity</name>
		<displayname>Engine Rumble Low Intensity</displayname>
		<value Craft="PropellerAircraft">0.06</value>
		<value Craft="TurbopropAircraft">0.06</value>
		<datatype>float</datatype>
		<Global>true</Global>
		<joystick>true</joystick>
		<pedals>true</pedals>
		<collective>true</collective>
		<info>peak intenstiy of engine rumble at low RPM threshold</info>
	</defaults>
	<defaults>
		<Grouping>ETL</Grouping>
		<name>etl_effect_intensity</name>
		<displayname>ETL Effect</displayname>
		<value Craft="Helicopter">0.25</value>
		<value Craft="HPGHelicopter">0.15</value>
		<datatype>float</datatype>
		<DCS>true</DCS>
		<MSFS>true</MSFS>
		<joystick>true</joystick>
		<pedals>true</pedals>
		<collective>true</collective>
	</defaults>
	<defaults>
		<Grouping>ETL</Grouping>
		<name>etl_start_speed</name>
		<displayname>ETL Start Speed</displayname>
		<value Craft="Helicopter">8</value>
		<value Craft="HPGHelicopter">8</value>
		<datatype>int</datatype>
		<unit>m/s</unit>
		<DCS>true</DCS>
		<MSFS>true</MSFS>
		<joystick>true</joystick>
		<pedals>true</pedals>
		<collective>true</collective>
		<info>speed at which the ETL effect will start - m/s</info>
	</defaults>
	<defaults>
		<Grouping>ETL</Grouping>
		<name>etl_stop_speed</name>
		<displayname>ETL Stop Speed</displayname>
		<value Craft="Helicopter">16</value>
		<value Craft="HPGHelicopter">16</value>
		<datatype>int</datatype>
		<unit>m/s</unit>
		<DCS>true</DCS>
		<MSFS>true</MSFS>
		<joystick>true</joystick>
		<pedals>true</pedals>
		<collective>true</collective>
		<info>speed at which the ETL effect will stop - m/s</info>
	</defaults>
	<defaults>
		<Grouping>FlyByWire</Grouping>
		<name>fbw_aileron_gain</name>
		<displayname>FBW Aileron Gain</displayname>
		<value>0.6</value>
		<datatype>float</datatype>
		<MSFS>true</MSFS>
		<joystick>true</joystick>
		<info>Fixed spring gain for FBW aircraft</info>
	</defaults>
	<defaults>
		<Grouping>FlyByWire</Grouping>
		<name>fbw_elevator_gain</name>
		<displayname>FBW Elevator Gain</displayname>
		<value>0.6</value>
		<datatype>float</datatype>
		<MSFS>true</MSFS>
		<joystick>true</joystick>
		<info>Fixed spring gain for FBW aircraft</info>
		</defaults>
	<defaults>
		<Grouping>FlyByWire</Grouping>
		<name>fbw_rudder_gain</name>
		<displayname>FBW Rudder Gain</displayname>
		<value>0.5</value>
		<datatype>float</datatype>
		<MSFS>true</MSFS>
		<pedals>true</pedals>
		<info>Fixed spring gain for FBW aircraft</info>
		</defaults>
	<defaults>
		<Grouping>Movement</Grouping>
		<name>flaps_motion_intensity</name>
		<displayname>Flaps Motion</displayname>
		<value>0.2</value>
		<datatype>float</datatype>
		<Global>true</Global>
		<joystick>true</joystick>
		<pedals>true</pedals>
		<info>peak vibration intensity when flaps are moving, 0 to disable</info>
	</defaults>
	<defaults>
		<Grouping>Basic</Grouping>
		<name>force_trim_button</name>
		<displayname>Force Trim Button</displayname>
		<value>99</value>
		<datatype>int</datatype>
		<MSFS>true</MSFS>
		<joystick>true</joystick>
		<collective>true</collective>
	</defaults>
	<defaults>
		<Grouping>Basic</Grouping>
		<name>force_trim_reset_button</name>
		<displayname>Force Trim Reset Button</displayname>
		<value>99</value>
		<datatype>int</datatype>
		<MSFS>true</MSFS>
		<joystick>true</joystick>
		<collective>true</collective>
	</defaults>
	<defaults>
		<Grouping>Buffeting</Grouping>
		<name>gear_buffet_intensity</name>
		<displayname>Gear Buffet</displayname>
		<value>0.15</value>
		<datatype>float</datatype>
		<DCS>true</DCS>
		<MSFS>true</MSFS>
		<joystick>true</joystick>
		<info>Peak intensity for gear drag buffeting effect</info>
		</defaults>
	<defaults>
		<Grouping>Movement</Grouping>
		<name>gear_motion_intensity</name>
		<displayname>Gear Motion</displayname>
		<value>0.15</value>
		<datatype>float</datatype>
		<Global>true</Global>
		<joystick>true</joystick>
		<pedals>true</pedals>
		<info>peak vibration intensity when gear is moving, 0 to disable</info>
	</defaults>
	<defaults>
		<Grouping>G Force</Grouping>
		<name>gforce_effect_curvature</name>
		<displayname>G Force Curvature</displayname>
		<value>2.0</value>
		<datatype>float</datatype>
		<DCS>true</DCS>
		<IL2>true</IL2>
		<joystick>true</joystick>
	</defaults>
	<defaults><Grouping>G Force</Grouping><name>gforce_effect_enable</name><displayname>G Force Effect Enable</displayname><value>true</value><datatype>bool</datatype><IL2>true</IL2><joystick>true</joystick></defaults>
	<defaults>
		<Grouping>G Force</Grouping>
		<name>gforce_effect_max_intensity</name>
		<displayname>G Force Max Intensity</displayname>
		<value>1.0</value>
		<datatype>float</datatype>
		<DCS>true</DCS>
		<IL2>true</IL2>
		<joystick>true</joystick>
		</defaults>
	<defaults>
		<Grouping>G Force</Grouping>
		<name>gforce_max_gs</name>
		<displayname>Maximum Gs</displayname>
		<value>7.0</value>
		<datatype>float</datatype>
		<DCS>true</DCS>
		<IL2>true</IL2>
		<joystick>true</joystick>
		</defaults>
	<defaults>
		<Grouping>G Force</Grouping>
		<name>gforce_min_gs</name>
		<displayname>Minimum Gs</displayname>
		<value>1.0</value>
		<datatype>float</datatype>
		<DCS>true</DCS>
		<IL2>true</IL2>
		<joystick>true</joystick>
	</defaults>
	<defaults>
		<Grouping>Weapons</Grouping>
		<name>gun_vibration_intensity</name>
		<displayname>Gun Vibration</displayname>
		<value>0.2</value>
		<datatype>float</datatype>
		<DCS>true</DCS>
		<joystick>true</joystick>
		<info>peak intenstiy for gunfire effect, 0 to disable</info>
	</defaults>
	<defaults>
		<Grouping>Autopilot</Grouping>
		<name>hands_off_deadzone</name>
		<displayname>Hands Off Deadzone</displayname>
		<value>0.02</value>
		<datatype>float</datatype>
		<MSFS>true</MSFS>
		<joystick>true</joystick>
		<pedals>true</pedals>
		<collective>true</collective>
	</defaults>
	<defaults>
		<Grouping>Autopilot</Grouping>
		<name>hands_on_deadzone</name>
		<displayname>Hands On Deadzone</displayname>
		<value>0.1</value>
		<datatype>float</datatype>
		<MSFS>true</MSFS>
		<joystick>true</joystick>
		<pedals>true</pedals>
		<collective>true</collective>
	</defaults>
	<defaults>
		<Grouping>Engine</Grouping>
		<name>heli_engine_rumble_intensity</name>
		<displayname>Heli Engine Rumble Intensity</displayname>
		<value Craft="Helicopter">0.12</value>
		<value Craft="HPGHelicopter">0.12</value>
		<datatype>float</datatype>
		<DCS>true</DCS>
		<MSFS>true</MSFS>
		<joystick>true</joystick>
		<pedals>true</pedals>
		<collective>true</collective>
		<info>peak rumble intensity for helicopter engine/rotor effect</info>
	</defaults>
	<defaults>
		<Grouping>Buffeting</Grouping>
		<name>il2_buffeting_factor</name><IL2>true</IL2><joystick>true</joystick>
		<displayname>Buffeting Factor	</displayname>
		<value>1.0</value>
		<datatype>float</datatype>
		<info></info>
		</defaults>
	<defaults>
		<Grouping>Basic</Grouping>
		<name>il2_cfg_validation</name>
		<displayname>IL2 Config Validation</displayname>
		<value>true</value>
		<datatype>bool</datatype>
		<IL2>true</IL2>
		<joystick>true</joystick>
		<pedals>true</pedals>
		<info>enable/disable validation of the IL-2 config</info>
	</defaults>
	<defaults>
		<Grouping>Buffeting</Grouping>
		<name>il2_enable_buffet</name>
		<displayname>Enable Buffeting</displayname>
		<value>true</value>
		<datatype>bool</datatype>
		<IL2>true</IL2>
		<joystick>true</joystick>
	</defaults>
	<defaults>
		<Grouping>Movement</Grouping>
		<name>il2_enable_runway_rumble</name>
		<displayname>Enable Runway Rumble</displayname>
		<value>true</value>
		<datatype>bool</datatype>
		<IL2>true</IL2>
		<joystick>true</joystick>
		<pedals>true</pedals>
	</defaults>
	<defaults>
		<Grouping>Weapons</Grouping>
		<name>il2_enable_weapons</name>
		<displayname>Enable Weapon Effects</displayname>
		<value>true</value>
		<datatype>bool</datatype>
		<IL2>true</IL2>
		<joystick>true</joystick>
		<pedals>true</pedals>
	</defaults>
	<defaults>
		<Grouping>System</Grouping>
		<name>il2_enabled</name>
		<displayname>Enable IL2</displayname>
		<value>false</value>
		<datatype>bool</datatype>
		<Global>true</Global>
		<joystick>true</joystick>
		<pedals>true</pedals>
		<info>can also run app with '-s IL2' argument.  See the VPforce manual for details on setting up TelemFFB for IL-2 </info>
	</defaults>
	<defaults>
		<Grouping>Basic</Grouping>
		<name>il2_path</name>
		<displayname>IL2 Path</displayname>
		<value>'C:\Program Files\IL-2 Sturmovik Great Battles'</value>
		<datatype>text</datatype>
		<IL2>true</IL2>
		<joystick>true</joystick>
		<pedals>true</pedals>
		<info>Path to IL2 root directory</info>
	</defaults>
	<defaults>
		<Grouping>Buffeting</Grouping>
		<name>il2_shake_master</name>
		<displayname>Effects Master Control</displayname>
		<value>false</value>
		<datatype>bool</datatype>
		<IL2>true</IL2>
		<joystick>true</joystick>
		<pedals>true</pedals>
		<info>master control for effects which are already in IL-2 (weapons, runway, buffet).  If enabled, recommend to disable shake effects in sim config</info>
	</defaults>
	<defaults>
		<Grouping>Basic</Grouping>
		<name>il2_telem_port</name>
		<displayname>IL2 Telemetry Port</displayname>
		<value>34385</value>
		<datatype>int</datatype>
		<IL2>true</IL2>
		<joystick>true</joystick>
		<pedals>true</pedals>
		<info>port number for Il-2 telemetry senders</info>
	</defaults>
	<defaults>
		<Grouping>Autopilot</Grouping>
		<name>invert_ap_x_axis</name>
		<displayname>Invert Aileron Autopilot Axis</displayname>
		<value>false</value>
		<datatype>bool</datatype>
		<MSFS>true</MSFS>
		<joystick>true</joystick>
	</defaults>
	<defaults>
		<Grouping>Engine</Grouping>
		<name>jet_engine_rumble_freq</name>
		<displayname>Jet Engine Rumble Freq</displayname>
		<value Craft="Helicopter">45</value>
		<value Craft="HPGHelicopter">45</value>
		<value Craft="JetAircraft">45</value>
		<value Craft="TurbopropAircraft">45</value>
		<datatype>int</datatype>
		<unit>hz</unit>
		<Global>true</Global>
		<joystick>true</joystick>
		<pedals>true</pedals>
		<collective>true</collective>
		<info>Most DCS helos are jet driven, enable the jet engine effect</info>
	</defaults>
	<defaults>
		<Grouping>Engine</Grouping>
		<name>jet_engine_rumble_intensity</name>
		<displayname>Jet Engine Rumble</displayname>
		<value Craft="Helicopter">0.01</value>
		<value Craft="HPGHelicopter">0.01</value>
		<value Craft="JetAircraft">0.05</value>
		<value Craft="TurbopropAircraft">0.03</value>
		<datatype>float</datatype>
		<Global>true</Global>
		<joystick>true</joystick>
		<pedals>true</pedals>
		<collective>true</collective>
	</defaults>
	<defaults>
		<Grouping>Axis Control</Grouping>
		<name>joystick_trim_follow_gain_physical_x</name>
		<displayname>Aileron Trim Gain (physical)</displayname>
		<value Craft="Default">1.0</value>
		<value Craft="Helicopter">0.4</value>
		<datatype>negfloat</datatype>
		<MSFS>true</MSFS>
		<joystick>true</joystick>
	</defaults>
	<defaults>
		<Grouping>Axis Control</Grouping>
		<name>joystick_trim_follow_gain_physical_y</name>
		<displayname>Elevator Trim Gain (physical)</displayname>
		<value Craft="Default">1.0</value>
		<value Craft="Helicopter">0.4</value>
		<datatype>negfloat</datatype>
		<MSFS>true</MSFS>
		<joystick>true</joystick>
	</defaults>
	<defaults>
		<Grouping>Axis Control</Grouping>
		<name>joystick_trim_follow_gain_virtual_x</name>
		<displayname>Aileron Trim Gain (virtual)</displayname>
		<value Craft="Default">0.2</value>
		<value Craft="Helicopter">0.3</value>
		<datatype>negfloat</datatype>
		<MSFS>true</MSFS>
		<joystick>true</joystick>
	</defaults>
	<defaults>
		<Grouping>Axis Control</Grouping>
		<name>joystick_trim_follow_gain_virtual_y</name>
		<displayname>Elevator Trim Gain (virtual)</displayname>
		<value Craft="Default">0.2</value>
		<value Craft="Helicopter">0.3</value>
		<datatype>negfloat</datatype>
		<MSFS>true</MSFS>
		<joystick>true</joystick>
	</defaults>
	<defaults>
		<Grouping>Axis Control</Grouping>
		<name>joystick_x_axis_scale</name>
		<displayname>Aileron (X) Axis Scale</displayname>
		<value>1.0</value>
		<datatype>float</datatype>
		<MSFS>true</MSFS>
		<joystick>true</joystick>
	</defaults>
	<defaults>
		<Grouping>Axis Control</Grouping>
		<name>joystick_y_axis_scale</name>
		<displayname>Elevator (Y) Axis Scale</displayname>
		<value>1.0</value>
		<datatype>float</datatype>
		<MSFS>true</MSFS>
		<joystick>true</joystick>
	</defaults>
	<defaults>
		<Grouping>System</Grouping>
		<name>logging_level</name>
		<displayname>Logging Level</displayname>
		<value>INFO</value>
		<datatype>text</datatype>
		<Global>true</Global>
		<joystick>true</joystick>
		<pedals>true</pedals>
		<collective>true</collective>
		<validvalues>DEBUG,INFO,WARNING,ERROR,CRITICAL</validvalues>
		<info></info>
	</defaults>
	<defaults>
		<Grouping>System</Grouping>
		<name>msfs_enabled</name>
		<displayname>Enable MSFS</displayname>
		<value>false</value>
		<datatype>bool</datatype>
		<Global>true</Global>
		<joystick>true</joystick>
		<pedals>true</pedals>
		<info>can also run app with '-s DCS' argument</info>
	</defaults>
	<defaults>
		<Grouping>Movement</Grouping>
		<name>nosewheel_shimmy</name>
		<displayname>Enable Nosewheel Shimmy</displayname>
		<value>false</value>
		<datatype>bool</datatype>
		<MSFS>true</MSFS>
		<pedals>true</pedals>
	</defaults>
	<defaults>
		<Grouping>Movement</Grouping>
		<name>nosewheel_shimmy_intensity</name>
		<displayname>Nosewheel Shimmy</displayname>
		<value>0.15</value>
		<datatype>float</datatype>
		<MSFS>true</MSFS>
		<pedals>true</pedals>
	</defaults>
	<defaults>
		<Grouping>Movement</Grouping>
		<name>nosewheel_shimmy_min_brakes</name>
		<displayname>Nosewheel Shimmy min brakes</displayname>
		<value>0.65</value>
		<datatype>float</datatype>
		<MSFS>true</MSFS>
		<pedals>true</pedals>
		</defaults>
	<defaults>
		<Grouping>Movement</Grouping>
		<name>nosewheel_shimmy_min_speed</name>
		<displayname>Nosewheel Shimmy min speed</displayname>
		<value>7</value>
		<unit>m/s</unit>
		<datatype>int</datatype>
		<MSFS>true</MSFS>
		<pedals>true</pedals>
	</defaults>
	<defaults>
		<Grouping>Buffeting</Grouping>
		<name>overspeed_shake_intensity</name>
		<displayname>Overpeed Shake Intensity</displayname>
		<value Craft="Helicopter">0.2</value>
		<value Craft="HPGHelicopter">0.2</value>
		<datatype>float</datatype>
		<DCS>true</DCS>
		<MSFS>true</MSFS>
		<joystick>true</joystick>
		<pedals>true</pedals>
		<collective>true</collective>
	</defaults>
	<defaults>
		<Grouping>Buffeting</Grouping>
		<name>overspeed_shake_start</name>
		<displayname>Overpeed Shake Start Speed</displayname>
		<value Craft="Helicopter">80</value>
		<value Craft="HPGHelicopter">80</value>
		<datatype>int</datatype>
		<unit>m/s</unit>
		<DCS>true</DCS>
		<MSFS>true</MSFS>
		<joystick>true</joystick>
		<pedals>true</pedals>
		<collective>true</collective>
	</defaults>
	<defaults>
		<Grouping>SpringCenter</Grouping>
		<name>pedal_dampening_gain</name>
		<displayname>Pedal Dampening Gain</displayname>
		<value Craft="JetAircraft">0.5</value>
		<value Craft="PropellerAircraft">0.6</value>
		<value Craft="Helicopter">0.1</value>
		<datatype>float</datatype>
		<DCS>true</DCS>
		<pedals>true</pedals>
		<info>Percent of damper setting in VPConf</info>
	</defaults>
	<defaults>
		<Grouping>SpringCenter</Grouping>
		<name>pedal_spring_gain</name>
		<displayname>Pedal Spring Gain</displayname>
		<value Craft="JetAircraft">0.6</value>
		<value Craft="PropellerAircraft">1.0</value>
		<value Craft="Helicopter">0.3</value>
		<datatype>float</datatype>
		<DCS>true</DCS>
		<pedals>true</pedals>
		<info>Percent of spring setting in VPConf</info>
	</defaults>
	<defaults>
		<Grouping>SpringCenter</Grouping>
		<name>pedal_spring_mode</name>
		<displayname>Pedal Spring Mode</displayname>
		<value Craft="JetAircraft">2</value>
		<value Craft="PropellerAircraft">3</value>
		<value Craft="Helicopter">1</value>
		<datatype>int</datatype>
		<DCS>true</DCS>
		<pedals>true</pedals>
		<validvalues>0,1,2,3</validvalues>
		<info>0=dcs default, 1=spring disabled, 2=static. Spring enabled using "pedal_spring_gain" spring setting, 3=dynamic and V speeds</info>
	</defaults>
	<defaults>
		<Grouping>SpringCenter</Grouping>
		<name>pedal_trimming_enabled</name>
		<displayname>Enable Pedal Trimming</displayname>
		<value Craft="Default">true</value>
		<value Craft="Helicopter">false</value>
		<datatype>bool</datatype>
		<DCS>true</DCS>
		<pedals>true</pedals>
	</defaults>
	<defaults>
		<Grouping>Prop</Grouping>
		<name>prop_diameter</name>
		<displayname>Prop Diameter</displayname>
		<value Craft="PropellerAircraft">1.7</value>
		<value Craft="TurbopropAircraft">2.7</value>
		<datatype>float</datatype>
		<unit>m</unit>
		<MSFS>true</MSFS>
		<joystick>true</joystick>
		<pedals>true</pedals>
	</defaults>
	<defaults>
		<Grouping>Prop</Grouping>
		<name>rotor_blade_count</name>
		<displayname>Rotor Blade Count</displayname>
		<value Craft="Helicopter">2</value>
		<value Craft="HPGHelicopter">4</value>
		<datatype>int</datatype>
		<DCS>true</DCS>
		<MSFS>true</MSFS>
		<joystick>true</joystick>
		<pedals>true</pedals>
		<collective>true</collective>
	</defaults>
	<defaults>
		<Grouping>Engine</Grouping>
		<name>rpm_scale</name>
		<displayname>RPM Scale</displayname>
		<value>1.0</value>
		<datatype>float</datatype>
		<Global>true</Global>
		<joystick>true</joystick>
		<pedals>true</pedals>
		<collective>true</collective>
	</defaults>
	<defaults>
		<Grouping>Basic</Grouping>
		<name>rudder_area</name>
		<displayname>Rudder Area</displayname>
		<value Craft="PropellerAircraft">0.8</value>
		<value Craft="TurbopropAircraft">1.2</value>
		<datatype>float</datatype>
		<pedals>true</pedals>
		<info>square meters</info>
	</defaults>
	<defaults>
		<Grouping>Basic</Grouping>
		<name>rudder_gain</name>
		<displayname>Rudder Gain</displayname>
		<value Craft="Default">0.3</value>
		<value Craft="TurbopropAircraft">0.3</value>
		<datatype>float</datatype>
		<MSFS>true</MSFS>
		<pedals>true</pedals>
	</defaults>
	<defaults>
		<Grouping>Prop</Grouping>
		<name>rudder_prop_flow_ratio</name>
		<displayname>Rudder Prop Flow</displayname>
		<value Craft="PropellerAircraft">0.2</value>
		<value Craft="TurbopropAircraft">0.2</value>
		<datatype>float</datatype>
		<MSFS>true</MSFS>
		<pedals>true</pedals>
	</defaults>
	<defaults>
		<Grouping>SpringCenter</Grouping>
		<name>rudder_spring_gain</name>
		<displayname>Rudder Spring Gain</displayname>
		<value Craft="GliderAircraft">0.25</value>
		<value Craft="TurbopropAircraft">0.4</value><pedals>true</pedals>
		<datatype>float</datatype>
		<MSFS>true</MSFS>
	</defaults>
	<defaults>
		<Grouping>Axis Control</Grouping>
		<name>rudder_trim_follow_gain_physical_x</name>
		<displayname>Rudder Trim Gain (physical)</displayname>
		<value>1.0</value>
		<datatype>negfloat</datatype>
		<MSFS>true</MSFS>
		<pedals>true</pedals>
	</defaults>
	<defaults>
		<Grouping>Axis Control</Grouping>
		<name>rudder_trim_follow_gain_virtual_x</name>
		<displayname>Rudder Trim Gain (virtual)</displayname>
		<value>0.2</value>
		<datatype>negfloat</datatype>
		<MSFS>true</MSFS>
		<pedals>true</pedals>
	</defaults>
	<defaults>
		<Grouping>Axis Control</Grouping>
		<name>rudder_x_axis_scale</name>
		<displayname>Rudder (X) Axis Scale</displayname>
		<value>1.0</value>
		<datatype>float</datatype>
		<MSFS>true</MSFS>
		<pedals>true</pedals>
		</defaults>
	<defaults>
		<Grouping>Movement</Grouping>
		<name>runway_rumble_intensity</name>
		<displayname>Runway Rumble</displayname>
		<value>0.2</value>
		<datatype>float</datatype>
		<DCS>true</DCS>
		<joystick>true</joystick>
		<info>peak runway intensity, 0 to disable</info>
		</defaults>
	<defaults>
		<Grouping>Buffeting</Grouping>
		<name>speedbrake_buffet_intensity</name>
		<displayname>Speedbrake Buffet</displayname>
		<value>0.15</value>
		<datatype>float</datatype>
		<DCS>true</DCS>
		<joystick>true</joystick>
		<info>Peak intensity for speed brake buffeting effect</info>
	</defaults>
	<defaults>
		<Grouping>Movement</Grouping>
		<name>speedbrake_motion_intensity</name>
		<displayname>Speedbrake Motion</displayname>
		<value>0.2</value>
		<datatype>float</datatype>
		<DCS>true</DCS>
		<joystick>true</joystick>
		<info>peak vibration intensity when speed brake is moving</info>
	</defaults>
	<defaults>
		<Grouping>Buffeting</Grouping>
		<name>spoiler_buffet_intensity</name>
		<displayname>Speedbrake Buffet</displayname>
		<value>0.2</value>
		<datatype>float</datatype>
		<MSFS>true</MSFS>
		<joystick>true</joystick>
		<info>peak buffeting intensity when spoilers deployed,  0 to disable</info>
	</defaults>
	<defaults>
		<Grouping>Buffeting</Grouping>
		<name>spoiler_buffet_intensity</name>
		<displayname>Spoiler Buffet</displayname>
		<value>0.2</value>
		<datatype>float</datatype>
		<DCS>true</DCS>
		<MSFS>true</MSFS>
		<joystick>true</joystick>
		<info>peak buffeting intensity when spoilers deployed,  0 to disable</info>
	</defaults>
	<defaults>
		<Grouping>Movement</Grouping>
		<name>spoiler_motion_intensity</name>
		<displayname>Speedbrake Motion</displayname>
		<value>0.2</value>
		<datatype>float</datatype>
		<MSFS>true</MSFS>
		<joystick>true</joystick>
		<info>F14 Only, peak vibration intensity when spoilers is moving, 0 to disable</info>
	</defaults>
	<defaults>
		<Grouping>Movement</Grouping>
		<name>spoiler_motion_intensity</name>
		<displayname>Spoiler Motion</displayname>
		<value>0.2</value>
		<datatype>float</datatype>
		<DCS>true</DCS>
		<MSFS>true</MSFS>
		<joystick>true</joystick>
		<info>F14 Only, peak vibration intensity when spoilers is moving, 0 to disable</info>
	</defaults>
	<defaults>
		<Grouping>Buffeting</Grouping>
		<unit>m/s</unit>
		<name>stall_aoa</name>
		<displayname>Stall AoA</displayname>
		<value>15</value>
		<datatype>int</datatype>
		<DCS>true</DCS>
		<joystick>true</joystick>
		<info>Stall AoA</info>
	</defaults>
	<defaults>
		<Grouping>Basic</Grouping>
		<name>telemetry_timeout</name>
		<displayname>Telemetry Timeout</displayname>
		<value>200</value>
		<datatype>int</datatype>
		<unit>ms</unit>
		<MSFS>true</MSFS>
		<joystick>true</joystick>
		<pedals>true</pedals>
		<collective>true</collective>
		<info>increase only if low frame-rate resulting in lost effects/control forces due to timeout</info>
	</defaults>
	<defaults>
		<Grouping>Axis Control</Grouping>
		<name>telemffb_controls_axes</name>
		<displayname>Enable Axis Control</displayname>
		<value Craft="Default">false</value>
		<value Craft="HPGHelicopter">true</value>
		<datatype>bool</datatype>
		<MSFS>true</MSFS>
		<joystick>true</joystick>
		<pedals>true</pedals>
		<collective>true</collective>
		<info>TelemFFB sends axis position to sim.  Do not assign in game or SPAD.next</info>
	</defaults>
	<defaults>
		<Grouping>Basic</Grouping>
		<name>trim_workaround</name>
		<displayname>Trim Workaround</displayname>
		<value>false</value>
		<datatype>bool</datatype>
		<DCS>true</DCS>
		<joystick>true</joystick>
	</defaults>
	<defaults>
		<Grouping>Basic</Grouping>
		<name>type</name>
		<displayname>Class</displayname>
		<value Craft="PropellerAircraft">PropellerAircraft</value>
		<value Craft="TurbopropAircraft">TurbopropAircraft</value>
		<value Craft="JetAircraft">JetAircraft</value>
		<value Craft="GliderAircraft">GliderAircraft</value>
		<value Craft="Helicopter">Helicopter</value>
		<value Craft="HPGHelicopter">HPGHelicopter</value>
		<datatype>text</datatype>
		<MSFS>true</MSFS>
		<joystick>true</joystick>
		<pedals>true</pedals>
		<collective>true</collective>
		<validvalues>PropellerAircraft,TurbopropAircraft,JetAircraft,Helicopter,HPGHelicopter,GlicerAircraft</validvalues>
		<info>HPGHelicopter is MSFS Hype Performace Group heli's only</info>
	</defaults>
	<defaults>
		<Grouping>Basic</Grouping>
		<name>type</name>
		<displayname>Class</displayname>
		<value Craft="PropellerAircraft">PropellerAircraft</value>
		<value Craft="JetAircraft">JetAircraft</value>
		<datatype>text</datatype>
		<IL2>true</IL2>
		<joystick>true</joystick>
		<pedals>true</pedals>
		<validvalues>PropellerAircraft,JetAircraft</validvalues>
		<info>Aircraft Type</info>
	</defaults>
	<defaults>
		<Grouping>Basic</Grouping>
		<name>type</name>
		<displayname>Class</displayname>
		<value Craft="PropellerAircraft">PropellerAircraft</value>
		<value Craft="JetAircraft">JetAircraft</value>
		<value Craft="Helicopter">Helicopter</value>
		<datatype>text</datatype>
		<DCS>true</DCS>
		<joystick>true</joystick>
		<pedals>true</pedals>
		<collective>true</collective>
		<validvalues>PropellerAircraft,JetAircraft,Helicopter</validvalues>
		<info>Aircraft Type</info>
	</defaults>
	<defaults>
		<Grouping>System</Grouping>
		<name>vpconf</name>
		<displayname>Configurator File</displayname>
		<value></value>
		<datatype>text</datatype>
		<Global>true</Global>
		<joystick>true</joystick>
		<pedals>true</pedals>
		<collective>true</collective>
	</defaults>
	<defaults>
		<Grouping>Weapons</Grouping>
		<name>weapon_effect_direction</name>
		<displayname>Weapon Effect Direction</displayname>
		<value>-1</value>
		<datatype>int</datatype>
		<DCS>true</DCS>
		<joystick>true</joystick>
		<info>Direction of applied force for weapons effects | range 0-359 or set to -1 for random</info>
	</defaults>
	<defaults>
		<Grouping>Weapons</Grouping>
		<name>weapon_release_intensity</name>
		<displayname>Weapon Release</displayname>
		<value>0.2</value>
		<datatype>float</datatype>
		<DCS>true</DCS>
		<IL2>true</IL2>
		<joystick>true</joystick>
		<pedals>true</pedals>
		<info>peak intensity for weapons release effect, 0 to disable</info>
		</defaults>
	<defaults>
		<Grouping>Buffeting</Grouping>
		<name>wind_effect_enabled</name>
		<displayname>Enable Wind Effect</displayname>
		<value>false</value>
		<datatype>bool</datatype>
		<DCS>true</DCS>
		<joystick>true</joystick>
	</defaults>
	<defaults>
		<Grouping>Buffeting</Grouping>
		<name>wind_effect_max_intensity</name>
		<displayname>Wind Effect Max Inensity</displayname>
		<value>0.4</value>
		<datatype>float</datatype>
		<DCS>true</DCS>
		<joystick>true</joystick>
		<pedals>true</pedals>
		<info>Adjust the maximum intensity the wind effect can attain</info>
		</defaults>
	<defaults>
		<Grouping>Buffeting</Grouping>
		<name>wind_effect_scaling</name>
		<displayname>Wind Effect Scaling</displayname>
		<value>1.0</value>
		<datatype>float</datatype>
		<DCS>true</DCS>
		<joystick>true</joystick>
		<info>Adjust the overall intensity of the wind effect</info>
	</defaults>
	<models>
		<setting>etl_effect_intensity</setting>
		<model>222B.*</model>
		<value>0.1</value>
		<sim>MSFS</sim>
		<device>joystick</device>
		</models>
	<models>
		<setting>etl_start_speed</setting>
		<model>222B.*</model>
		<value>7</value>
		<unit>m/s</unit>
		<sim>MSFS</sim>
		<device>joystick</device>
	</models>
	<models>
		<setting>etl_stop_speed</setting>
		<model>222B.*</model>
		<value>14</value>
		<unit>m/s</unit>
		<sim>MSFS</sim>
		<device>joystick</device>
	</models>
	<models>
		<setting>overspeed_shake_start</setting>
		<model>222B.*</model>
		<value>70</value>
		<unit>m/s</unit>
		<sim>MSFS</sim>
		<device>joystick</device>
	</models>
	<models>
		<setting>rotor_blade_count</setting>
		<model>222B.*</model>
		<value>2</value>
		<sim>MSFS</sim>
		<device>joystick</device>
		</models>
	<models>
		<setting>runway_rumble_intensity</setting>
		<model>222B.*</model>
		<value>0.5</value>
		<sim>MSFS</sim>
		<device>joystick</device>
		</models>
	<models>
		<setting>type</setting>
		<model>222B.*</model>
		<value>Helicopter</value>
		<sim>MSFS</sim>
		<device>joystick</device>
	</models>
	<models>
		<setting>cyclic_spring_gain</setting>
		<model>500E.*</model>
		<value>0.5</value>
		<sim>MSFS</sim>
		<device>joystick</device>
	</models>
	<models>
		<setting>etl_effect_intensity</setting>
		<model>500E.*</model>
		<value>0.1</value>
		<sim>MSFS</sim>
		<device>joystick</device>
	</models>
	<models>
		<setting>etl_start_speed</setting>
		<model>500E.*</model>
		<value>7</value>
		<unit>m/s</unit>
		<sim>MSFS</sim>
		<device>joystick</device>
	</models>
	<models>
		<setting>etl_stop_speed</setting>
		<model>500E.*</model>
		<value>15</value>
		<unit>m/s</unit>
		<sim>MSFS</sim>
		<device>joystick</device>
	</models>
	<models>
		<setting>joystick_x_axis_scale</setting>
		<model>500E.*</model>
		<value>0.85</value>
		<sim>MSFS</sim>
		<device>joystick</device>
		</models>
	<models>
		<setting>joystick_y_axis_scale</setting>
		<model>500E.*</model>
		<value>0.85</value>
		<sim>MSFS</sim>
		<device>joystick</device>
	</models>
	<models>
		<setting>rotor_blade_count</setting>
		<model>500E.*</model>
		<value>5</value>
		<sim>MSFS</sim>
		<device>joystick</device>
	</models>
	<models>
		<setting>runway_rumble_intensity</setting>
		<model>500E.*</model>
		<value>0.5</value>
		<sim>MSFS</sim>
		<device>joystick</device>
	</models>
	<models>
		<setting>type</setting>
		<model>500E.*</model>
		<value>Helicopter</value>
		<sim>MSFS</sim>
		<device>joystick</device>
		</models>
	<models>
		<setting>type</setting>
		<model>A-10A.*</model>
		<value>JetAircraft</value>
		<sim>DCS</sim>
		<device>joystick</device>
		</models>
	<models>
		<setting>runway_rumble_intensity</setting>
		<model>A-10C.*</model>
		<value>2.0</value>
		<sim>DCS</sim>
		<device>joystick</device>
	</models>
	<models>
		<setting>type</setting>
		<model>A-10C.*</model>
		<value>JetAircraft</value>
		<sim>DCS</sim>
		<device>joystick</device>
	</models>
	<models>
		<setting>type</setting>
		<model>A-20B</model>
		<value>PropellerAircraft</value>
		<sim>IL2</sim>
		<device>joystick</device>
		</models>
	<models>
		<setting>aileron_gain</setting>
		<model>A2A Piper PA-24.*</model>
		<value>0.06</value>
		<sim>MSFS</sim>
		<device>joystick</device>
	</models>
	<models>
		<setting>elevator_droop_moment</setting>
		<model>A2A Piper PA-24.*</model>
		<value>0.2</value>
		<sim>MSFS</sim>
		<device>joystick</device>
		</models>
	<models>
		<setting>elevator_gain</setting>
		<model>A2A Piper PA-24.*</model>
		<value>0.4</value>
		<sim>MSFS</sim>
		<device>joystick</device>
	</models>
	<models>
		<setting>elevator_prop_flow_ratio</setting>
		<model>A2A Piper PA-24.*</model>
		<value>0.3</value>
		<sim>MSFS</sim>
		<device>joystick</device>
		</models>
	<models>
		<setting>joystick_trim_follow_gain_virtual_x</setting>
		<model>A2A Piper PA-24.*</model>
		<value>0.1</value>
		<sim>MSFS</sim>
		<device>joystick</device>
	</models>
	<models>
		<setting>joystick_trim_follow_gain_virtual_y</setting>
		<model>A2A Piper PA-24.*</model>
		<value>0.4</value>
		<sim>MSFS</sim>
		<device>joystick</device>
	</models>
	<models>
		<setting>rudder_gain</setting>
		<model>A2A Piper PA-24.*</model>
		<value>0.3</value>
		<sim>MSFS</sim>
		<device>pedals</device>
		</models>
	<models>
		<setting>type</setting>
		<model>A2A Piper PA-24.*</model>
		<value>PropellerAircraft</value>
		<sim>MSFS</sim>
		<device>joystick</device>
	</models>
	<models>
		<setting>joystick_trim_follow_gain_virtual_y</setting>
		<model>Aerosoft DHC-6.*</model>
		<value>0.35</value>
		<sim>MSFS</sim>
		<device>joystick</device>
		</models>
	<models>
		<setting>type</setting>
		<model>Aerosoft DHC-6.*</model>
		<value>TurbopropAircraft</value>
		<sim>MSFS</sim>
		<device>joystick</device>
		</models>
	<models>
		<setting>cm_vibration_intensity</setting>
		<model>AH-64D_BLK_II</model>
		<value>0.12</value>
		<sim>DCS</sim>
		<device>joystick</device>
	</models>
	<models>
		<setting>etl_effect_intensity</setting>
		<model>AH-64D_BLK_II</model>
		<value>0.3</value>
		<sim>DCS</sim>
		<device>joystick</device>
	</models>
	<models>
		<setting>etl_start_speed</setting>
		<model>AH-64D_BLK_II</model>
		<value>6</value>
		<unit>m/s</unit>
		<sim>DCS</sim>
		<device>joystick</device>
	</models>
	<models>
		<setting>etl_stop_speed</setting>
		<model>AH-64D_BLK_II</model>
		<value>22</value>
		<unit>m/s</unit>
		<sim>DCS</sim>
		<device>joystick</device>
	</models>
	<models>
		<setting>gun_vibration_intensity</setting>
		<model>AH-64D_BLK_II</model>
		<value>0.12</value>
		<unit></unit>
		<sim>DCS</sim>
		<device>joystick</device>
	</models>
	<models>
		<setting>type</setting>
		<model>AH-64D_BLK_II</model>
		<value>Helicopter</value>
		<sim>DCS</sim>
		<device>joystick</device>
		</models>
	<models>
		<setting>weapon_release_intensity</setting>
		<model>AH-64D_BLK_II</model>
		<value>0.12</value>
		<sim>DCS</sim>
		<device>joystick</device>
	</models>
	<models>
		<setting>cyclic_spring_gain</setting>
		<model>Airbus H145.*</model>
		<value>0.65</value>
		<sim>MSFS</sim>
		<device>joystick</device>
	</models>
	<models>
		<setting>etl_effect_intensity</setting>
		<model>Airbus H145.*</model>
		<value>0.1</value>
		<sim>MSFS</sim>
		<device>joystick</device>
	</models>
	<models>
		<setting>etl_start_speed</setting>
		<model>Airbus H145.*</model>
		<value>6</value>
		<unit>kt</unit>
		<sim>MSFS</sim>
		<device>joystick</device>
	</models>
	<models>
		<setting>etl_stop_speed</setting>
		<model>Airbus H145.*</model>
		<value>30</value>
		<unit>kt</unit>
		<sim>MSFS</sim>
		<device>joystick</device>
	</models>
	<models>
		<setting>overspeed_shake_start</setting>
		<model>Airbus H145.*</model>
		<value>75</value>
		<unit>m/s</unit>
		<sim>MSFS</sim>
		<device>joystick</device>
	</models>
	<models>
		<setting>rotor_blade_count</setting>
		<model>Airbus H145.*</model>
		<value>4</value>
		<sim>MSFS</sim>
		<device>joystick</device>
	</models>
	<models>
		<setting>runway_rumble_intensity</setting>
		<model>Airbus H145.*</model>
		<value>0.5</value>
		<sim>MSFS</sim>
		<device>joystick</device>
	</models>
	<models>
		<setting>type</setting>
		<model>Airbus H145.*</model>
		<value>HPGHelicopter</value>
		<sim>MSFS</sim>
		<device>joystick</device>
	</models>
	<models>
		<setting>type</setting>
		<model>Airbus H145.*</model>
		<value>HPGHelicopter</value>
		<sim>MSFS</sim>
		<device>collective</device>
		</models>
	<models>
		<setting>cyclic_spring_gain</setting>
		<model>Airbus H160.*</model>
		<value>0.65</value>
		<sim>MSFS</sim>
		<device>joystick</device>
	</models>
	<models>
		<setting>etl_effect_intensity</setting>
		<model>Airbus H160.*</model>
		<value>0.1</value>
		<sim>MSFS</sim>
		<device>joystick</device>
	</models>
	<models>
		<setting>etl_start_speed</setting>
		<model>Airbus H160.*</model>
		<value>6</value>
		<unit>kt</unit>
		<sim>MSFS</sim>
		<device>joystick</device>
	</models>
	<models>
		<setting>etl_stop_speed</setting>
		<model>Airbus H160.*</model>
		<value>30</value>
		<unit>kt</unit>
		<sim>MSFS</sim>
		<device>joystick</device>
	</models>
	<models>
		<setting>rotor_blade_count</setting>
		<model>Airbus H160.*</model>
		<value>5</value>
		<sim>MSFS</sim>
		<device>joystick</device>
	</models>
	<models>
		<setting>runway_rumble_intensity</setting>
		<model>Airbus H160.*</model>
		<value>0.5</value>
		<sim>MSFS</sim>
		<device>joystick</device>
	</models>
	<models>
		<setting>type</setting>
		<model>Airbus H160.*</model>
		<value>HPGHelicopter</value>
		<sim>MSFS</sim>
		<device>joystick</device>
	</models>
	<models>
		<setting>type</setting>
		<model>Airbus H160.*</model>
		<value>HPGHelicopter</value>
		<sim>MSFS</sim>
		<device>collective</device>
	</models>
	<models>
		<setting>runway_rumble_intensity</setting>
		<model>AJS37</model>
		<value>2.0</value>
		<sim>DCS</sim>
		<device>joystick</device>
	</models>
	<models>
		<setting>type</setting>
		<model>AJS37</model>
		<value>JetAircraft</value>
		<sim>DCS</sim>
		<device>joystick</device>
	</models>
	<models>
		<setting>etl_effect_intensity</setting>
		<model>Asobo Cabri G2</model>
		<value>0.25</value>
		<sim>MSFS</sim>
		<device>joystick</device>
	</models>
	<models>
		<setting>etl_start_speed</setting>
		<model>Asobo Cabri G2</model>
		<value>10</value>
		<unit>m/s</unit>
		<sim>MSFS</sim>
		<device>joystick</device>
	</models>
	<models>
		<setting>etl_stop_speed</setting>
		<model>Asobo Cabri G2</model>
		<value>15</value>
		<unit>m/s</unit>
		<sim>MSFS</sim>
		<device>joystick</device>
	</models>
	<models>
		<setting>overspeed_shake_start</setting>
		<model>Asobo Cabri G2</model>
		<value>75</value>
		<unit>m/s</unit>
		<sim>MSFS</sim>
		<device>joystick</device>
	</models>
	<models>
		<setting>rotor_blade_count</setting>
		<model>Asobo Cabri G2</model>
		<value>3</value>
		<sim>MSFS</sim>
		<device>joystick</device>
	</models>
	<models>
		<setting>runway_rumble_intensity</setting>
		<model>Asobo Cabri G2</model>
		<value>0.5</value>
		<sim>MSFS</sim>
		<device>joystick</device>
	</models>
	<models>
		<setting>type</setting>
		<model>Asobo Cabri G2</model>
		<value>Helicopter</value>
		<sim>MSFS</sim>
		<device>joystick</device>
	</models>
	<models>
		<setting>aileron_gain</setting>
		<model>Asobo DG1001E Neo</model>
		<value>0.1</value>
		<sim>MSFS</sim>
		<device>joystick</device>
	</models>
	<models>
		<setting>aileron_spring_gain</setting>
		<model>Asobo DG1001E Neo</model>
		<value>0.25</value>
		<sim>MSFS</sim>
		<device>joystick</device>
		</models>
	<models>
		<setting>aircraft_is_spring_centered</setting>
		<model>Asobo DG1001E Neo</model>
		<value>true</value>
		<sim>MSFS</sim>
		<device>joystick</device>
	</models>
	<models>
		<setting>elevator_gain</setting>
		<model>Asobo DG1001E Neo</model>
		<value>0.1</value>
		<sim>MSFS</sim>
		<device>joystick</device>
		</models>
	<models>
		<setting>elevator_spring_gain</setting>
		<model>Asobo DG1001E Neo</model>
		<value>0.25</value>
		<sim>MSFS</sim>
		<device>joystick</device>
	</models>
	<models>
		<setting>type</setting>
		<model>Asobo DG1001E Neo</model>
		<value>GliderAircraft</value>
		<sim>MSFS</sim>
		<device>joystick</device>
		</models>
	<models>
		<setting>type</setting>
		<model>Asobo Husky.*</model>
		<value>PropellerAircraft</value>
		<sim>MSFS</sim>
		<device>joystick</device>
		</models>
	<models>
		<setting>aileron_gain</setting>
		<model>Asobo LS8 18</model>
		<value>0.1</value>
		<sim>MSFS</sim>
		<device>joystick</device>
	</models>
	<models>
		<setting>aileron_spring_gain</setting>
		<model>Asobo LS8 18</model>
		<value>0.25</value>
		<sim>MSFS</sim>
		<device>joystick</device>
	</models>
	<models>
		<setting>aircraft_is_spring_centered</setting>
		<model>Asobo LS8 18</model>
		<value>true</value>
		<sim>MSFS</sim>
		<device>joystick</device>
	</models>
	<models>
		<setting>elevator_gain</setting>
		<model>Asobo LS8 18</model>
		<value>0.1</value>
		<sim>MSFS</sim>
		<device>joystick</device>
	</models>
	<models>
		<setting>elevator_spring_gain</setting>
		<model>Asobo LS8 18</model>
		<value>0.25</value>
		<sim>MSFS</sim>
		<device>joystick</device>
	</models>
	<models>
		<setting>type</setting>
		<model>Asobo LS8 18</model>
		<value>GliderAircraft</value>
		<sim>MSFS</sim>
		<device>joystick</device>
	</models>
	<models>
		<setting>aileron_gain</setting>
		<model>Asobo Savage Cub.*</model>
		<value>0.04</value>
		<sim>MSFS</sim>
		<device>joystick</device>
		</models>
	<models>
		<setting>elevator_droop_moment</setting>
		<model>Asobo Savage Cub.*</model>
		<value>0.2</value>
		<sim>MSFS</sim>
		<device>joystick</device>
	</models>
	<models>
		<setting>elevator_gain</setting>
		<model>Asobo Savage Cub.*</model>
		<value>0.7</value>
		<sim>MSFS</sim>
		<device>joystick</device>
		</models>
	<models>
		<setting>joystick_trim_follow_gain_virtual_y</setting>
		<model>Asobo Savage Cub.*</model>
		<value>0.4</value>
		<sim>MSFS</sim>
		<device>joystick</device>
		</models>
	<models>
		<setting>type</setting>
		<model>Asobo Savage Cub.*</model>
		<value>PropellerAircraft</value>
		<sim>MSFS</sim>
		<device>joystick</device>
		</models>
	<models>
		<setting>type</setting>
		<model>Asobo XCub</model>
		<value>PropellerAircraft</value>
		<sim>MSFS</sim>
		<device>joystick</device>
		</models>
	<models>
		<setting>runway_rumble_intensity</setting>
		<model>AV8BNA</model>
		<value>2.0</value>
		<sim>DCS</sim>
		<device>joystick</device>
	</models>
	<models>
		<setting>trim_workaround</setting>
		<model>AV8BNA</model>
		<value>true</value>
		<sim>DCS</sim>
		<device>joystick</device>
	</models>
	<models>
		<setting>type</setting>
		<model>AV8BNA</model>
		<value>JetAircraft</value>
		<sim>DCS</sim>
		<device>joystick</device>
		</models>
	<models>
		<setting>type</setting>
		<model>Aviat Husky A-1C.*</model>
		<value>PropellerAircraft</value>
		<sim>MSFS</sim>
		<device>joystick</device>
		</models>
	<models>
		<setting>aileron_gain</setting>
		<model>Beechcraft King Air.*</model>
		<value>0.1</value>
		<sim>MSFS</sim>
		<device>joystick</device>
	</models>
	<models>
		<setting>joystick_trim_follow_gain_virtual_y</setting>
		<model>Beechcraft King Air.*</model>
		<value>-0.2</value>
		<sim>MSFS</sim>
		<device>joystick</device>
		</models>
	<models>
		<setting>type</setting>
		<model>Beechcraft King Air.*</model>
		<value>TurbopropAircraft</value>
		<sim>MSFS</sim>
		<device>joystick</device>
		</models>
	<models>
		<setting>etl_effect_intensity</setting>
		<model>Bell 407.*</model>
		<value>0.25</value>
		<sim>MSFS</sim>
		<device>joystick</device>
	</models>
	<models>
		<setting>etl_start_speed</setting>
		<model>Bell 407.*</model>
		<value>8</value>
		<unit>m/s</unit>
		<sim>MSFS</sim>
		<device>joystick</device>
	</models>
	<models>
		<setting>etl_stop_speed</setting>
		<model>Bell 407.*</model>
		<value>13</value>
		<unit>m/s</unit>
		<sim>MSFS</sim>
		<device>joystick</device>
	</models>
	<models>
		<setting>overspeed_shake_start</setting>
		<model>Bell 407.*</model>
		<value>60</value>
		<unit>m/s</unit>
		<sim>MSFS</sim>
		<device>joystick</device>
	</models>
	<models>
		<setting>rotor_blade_count</setting>
		<model>Bell 407.*</model>
		<value>4</value>
		<sim>MSFS</sim>
		<device>joystick</device>
	</models>
	<models>
		<setting>runway_rumble_intensity</setting>
		<model>Bell 407.*</model>
		<value>0.1</value>
		<sim>MSFS</sim>
		<device>joystick</device>
	</models>
	<models>
		<setting>type</setting>
		<model>Bell 407.*</model>
		<value>Helicopter</value>
		<sim>MSFS</sim>
		<device>joystick</device>
		</models>
	<models>
		<setting>cyclic_spring_gain</setting>
		<model>Bell 429.*</model>
		<value>0.3</value>
		<sim>MSFS</sim>
		<device>joystick</device>
	</models>
	<models>
		<setting>cyclic_spring_gain</setting>
		<model>Bell 429.*</model>
		<value>0.6</value>
		<sim>MSFS</sim>
		<device>joystick</device>
	</models>
	<models>
		<setting>etl_effect_intensity</setting>
		<model>Bell 429.*</model>
		<value>0.15</value>
		<sim>MSFS</sim>
		<device>joystick</device>
	</models>
	<models>
		<setting>etl_effect_intensity</setting>
		<model>Bell 429.*</model>
		<value>0.2</value>
		<sim>MSFS</sim>
		<device>joystick</device>
	</models>
	<models>
		<setting>etl_start_speed</setting>
		<model>Bell 429.*</model>
		<value>14</value>
		<unit>kt</unit>
		<sim>MSFS</sim>
		<device>joystick</device>
	</models>
	<models>
		<setting>etl_start_speed</setting>
		<model>Bell 429.*</model>
		<value>8</value>
		<unit>kt</unit>
		<sim>MSFS</sim>
		<device>joystick</device>
	</models>
	<models>
		<setting>etl_stop_speed</setting>
		<model>Bell 429.*</model>
		<value>16</value>
		<unit>kt</unit>
		<sim>MSFS</sim>
		<device>joystick</device>
	</models>
	<models>
		<setting>etl_stop_speed</setting>
		<model>Bell 429.*</model>
		<value>20</value>
		<unit>kt</unit>
		<sim>MSFS</sim>
		<device>joystick</device>
	</models>
	<models>
		<setting>overspeed_shake_start</setting>
		<model>Bell 429.*</model>
		<value>45</value>
		<unit>m/s</unit>
		<sim>MSFS</sim>
		<device>joystick</device>
	</models>
	<models>
		<setting>overspeed_shake_start</setting>
		<model>Bell 429.*</model>
		<value>70</value>
		<unit>m/s</unit>
		<sim>MSFS</sim>
		<device>joystick</device>
	</models>
	<models>
		<setting>rotor_blade_count</setting>
		<model>Bell 429.*</model>
		<value>3</value>
		<sim>MSFS</sim>
		<device>joystick</device>
	</models>
	<models>
		<setting>rotor_blade_count</setting>
		<model>Bell 429.*</model>
		<value>4</value>
		<sim>MSFS</sim>
		<device>joystick</device>
	</models>
	<models>
		<setting>runway_rumble_intensity</setting>
		<model>Bell 429.*</model>
		<value>0.5</value>
		<sim>MSFS</sim>
		<device>joystick</device>
	</models>
	<models>
		<setting>runway_rumble_intensity</setting>
		<model>Bell 429.*</model>
		<value>0.5</value>
		<sim>MSFS</sim>
		<device>joystick</device>
	</models>
	<models>
		<setting>type</setting>
		<model>Bell 429.*</model>
		<value>Helicopter</value>
		<sim>MSFS</sim>
		<device>joystick</device>
	</models>
	<models>
		<setting>type</setting>
		<model>Bell 429.*</model>
		<value>Helicopter</value>
		<sim>MSFS</sim>
		<device>joystick</device>
	</models>
	<models>
		<setting>type</setting>
		<model>Bf 109.*</model>
		<value>PropellerAircraft</value>
		<sim>IL2</sim>
		<device>joystick</device>
		</models>
	<models>
		<setting>type</setting>
		<model>Bf 110.*</model>
		<value>PropellerAircraft</value>
		<sim>IL2</sim>
		<device>joystick</device>
		</models>
	<models>
		<setting>type</setting>
		<model>Bf-109K-4</model>
		<value>PropellerAircraft</value>
		<sim>DCS</sim>
		<device>joystick</device>
		</models>
	<models>
		<setting>aircraft_is_fbw</setting>
		<model>Boeing F/A 18.*</model>
		<value>true</value>
		<sim>MSFS</sim>
		<device>joystick</device>
		</models>
	<models>
		<setting>aoa_reduction_effect_enabled</setting>
		<model>Boeing F/A 18.*</model>
		<value>false</value>
		<sim>MSFS</sim>
		<device>joystick</device>
		</models>
	<models>
		<setting>aoa_reduction_max_force</setting>
		<model>Boeing F/A 18.*</model>
		<value>0.7</value>
		<sim>MSFS</sim>
		<device>joystick</device>
	</models>
	<models>
		<setting>critical_aoa_max</setting>
		<model>Boeing F/A 18.*</model>
		<value>25</value>
		<sim>MSFS</sim>
		<device>joystick</device>
		</models>
	<models>
		<setting>critical_aoa_start</setting>
		<model>Boeing F/A 18.*</model>
		<value>22</value>
		<sim>MSFS</sim>
		<device>joystick</device>
	</models>
	<models>
		<setting>fbw_aileron_gain</setting>
		<model>Boeing F/A 18.*</model>
		<value>0.6</value>
		<sim>MSFS</sim>
		<device>joystick</device>
	</models>
	<models>
		<setting>fbw_elevator_gain</setting>
		<model>Boeing F/A 18.*</model>
		<value>0.6</value>
		<sim>MSFS</sim>
		<device>joystick</device>
	</models>
	<models>
		<setting>flaps_motion_intensity</setting>
		<model>Boeing F/A 18.*</model>
		<value>0.0</value>
		<sim>MSFS</sim>
		<device>joystick</device>
		</models>
	<models>
		<setting>gear_buffet_intensity</setting>
		<model>Boeing F/A 18.*</model>
		<value>0.05</value>
		<sim>MSFS</sim>
		<device>joystick</device>
	</models>
	<models>
		<setting>spoiler_buffet_intensity</setting>
		<model>Boeing F/A 18.*</model>
		<value>0.1</value>
		<sim>MSFS</sim>
		<device>joystick</device>
	</models>
	<models>
		<setting>spoiler_motion_intensity</setting>
		<model>Boeing F/A 18.*</model>
		<value>0.2</value>
		<sim>MSFS</sim>
		<device>joystick</device>
	</models>
	<models>
		<setting>type</setting>
		<model>Boeing F/A 18.*</model>
		<value>JetAircraft</value>
		<sim>MSFS</sim>
		<device>joystick</device>
	</models>
	<models>
		<setting>rudder_gain</setting>
		<model>Carenado CT182T.*</model>
		<value>0.2</value>
		<sim>MSFS</sim>
		<device>joystick</device>
		</models>
	<models>
		<setting>type</setting>
		<model>Carenado CT182T.*</model>
		<value>PropellerAircraft</value>
		<sim>MSFS</sim>
		<device>joystick</device>
		</models>
	<models>
		<setting>aileron_gain</setting>
		<model>Cessna 152.*</model>
		<value>0.05</value>
		<sim>MSFS</sim>
		<device>joystick</device>
	</models>
	<models>
		<setting>elevator_droop_moment</setting>
		<model>Cessna 152.*</model>
		<value>0.3</value>
		<sim>MSFS</sim>
		<device>joystick</device>
	</models>
	<models>
		<setting>elevator_gain</setting>
		<model>Cessna 152.*</model>
		<value>0.8</value>
		<sim>MSFS</sim>
		<device>joystick</device>
	</models>
	<models>
		<setting>joystick_trim_follow_gain_virtual_y</setting>
		<model>Cessna 152.*</model>
		<value>-0.25</value>
		<sim>MSFS</sim>
		<device>joystick</device>
		</models>
	<models>
		<setting>type</setting>
		<model>Cessna 152.*</model>
		<value>PropellerAircraft</value>
		<sim>MSFS</sim>
		<device>joystick</device>
		</models>
	<models>
		<setting>aileron_gain</setting>
		<model>Cessna 172.*</model>
		<value>0.1</value>
		<sim>MSFS</sim>
		<device>joystick</device>
		</models>
	<models>
		<setting>invert_ap_x_axis</setting>
		<model>Cessna 172.*</model>
		<value>true</value>
		<sim>MSFS</sim>
		<device>joystick</device>
		</models>
	<models>
		<setting>joystick_trim_follow_gain_physical_x</setting>
		<model>Cessna 172.*</model>
		<value>0.0</value>
		<sim>MSFS</sim>
		<device>joystick</device>
		</models>
	<models>
		<setting>joystick_trim_follow_gain_virtual_x</setting>
		<model>Cessna 172.*</model>
		<value>0.1</value>
		<sim>MSFS</sim>
		<device>joystick</device>
	</models>
	<models>
		<setting>joystick_trim_follow_gain_virtual_y</setting>
		<model>Cessna 172.*</model>
		<value>0.4</value>
		<sim>MSFS</sim>
		<device>joystick</device>
	</models>
	<models>
		<setting>type</setting>
		<model>Cessna 172.*</model>
		<value>PropellerAircraft</value>
		<sim>MSFS</sim>
		<device>joystick</device>
		</models>
	<models>
		<setting>aileron_gain</setting>
		<model>Cessna Skyhawk.*</model>
		<value>0.04</value>
		<sim>MSFS</sim>
		<device>joystick</device>
	</models>
	<models>
		<setting>elevator_droop_moment</setting>
		<model>Cessna Skyhawk.*</model>
		<value>0.3</value>
		<sim>MSFS</sim>
		<device>joystick</device>
	</models>
	<models>
		<setting>invert_ap_x_axis</setting>
		<model>Cessna Skyhawk.*</model>
		<value>true</value>
		<sim>MSFS</sim>
		<device>joystick</device>
	</models>
	<models>
		<setting>joystick_trim_follow_gain_virtual_y</setting>
		<model>Cessna Skyhawk.*</model>
		<value>0.55</value>
		<sim>MSFS</sim>
		<device>joystick</device>
	</models>
	<models>
		<setting>type</setting>
		<model>Cessna Skyhawk.*</model>
		<value>PropellerAircraft</value>
		<sim>MSFS</sim>
		<device>joystick</device>
		</models>
	<models>
		<setting>joystick_trim_follow_gain_virtual_x</setting>
		<model>Cessna( 208B)? Grand Caravan.*</model>
		<value>0.5</value>
		<sim>MSFS</sim>
		<device>joystick</device>
		</models>
	<models>
		<setting>joystick_trim_follow_gain_virtual_y</setting>
		<model>Cessna( 208B)? Grand Caravan.*</model>
		<value>0.3</value>
		<sim>MSFS</sim>
		<device>joystick</device>
	</models>
	<models>
		<setting>type</setting>
		<model>Cessna( 208B)? Grand Caravan.*</model>
		<value>TurbopropAircraft</value>
		<sim>MSFS</sim>
		<device>joystick</device>
	</models>
	<models>
		<setting>joystick_trim_follow_gain_virtual_y</setting>
		<model>Cockspur C162.*</model>
		<value>-0.25</value>
		<sim>MSFS</sim>
		<device>joystick</device>
	</models>
	<models>
		<setting>type</setting>
		<model>Cockspur C162.*</model>
		<value>PropellerAircraft</value>
		<sim>MSFS</sim>
		<device>joystick</device>
		</models>
	<models>
		<setting>type</setting>
		<model>DA62.*</model>
		<value>PropellerAircraft</value>
		<sim>MSFS</sim>
		<device>joystick</device>
		</models>
	<models>
		<setting>joystick_trim_follow_gain_virtual_y</setting>
		<model>Douglas DC-3.*</model>
		<value>0.5</value>
		<sim>MSFS</sim>
		<device>joystick</device>
		</models>
	<models>
		<setting>type</setting>
		<model>Douglas DC-3.*</model>
		<value>PropellerAircraft</value>
		<sim>MSFS</sim>
		<device>joystick</device>
		</models>
	<models>
		<setting>etl_effect_intensity</setting>
		<model>Experimental Mini-500.*</model>
		<value>0.2</value>
		<sim>MSFS</sim>
		<device>joystick</device>
	</models>
	<models>
		<setting>etl_start_speed</setting>
		<model>Experimental Mini-500.*</model>
		<value>16</value>
		<unit>kt</unit>
		<sim>MSFS</sim>
		<device>joystick</device>
	</models>
	<models>
		<setting>etl_stop_speed</setting>
		<model>Experimental Mini-500.*</model>
		<value>24</value>
		<unit>kt</unit>
		<sim>MSFS</sim>
		<device>joystick</device>
	</models>
	<models>
		<setting>overspeed_shake_start</setting>
		<model>Experimental Mini-500.*</model>
		<value>45</value>
		<unit>m/s</unit>
		<sim>MSFS</sim>
		<device>joystick</device>
	</models>
	<models>
		<setting>rotor_blade_count</setting>
		<model>Experimental Mini-500.*</model>
		<value>2</value>
		<sim>MSFS</sim>
		<device>joystick</device>
	</models>
	<models>
		<setting>runway_rumble_intensity</setting>
		<model>Experimental Mini-500.*</model>
		<value>0.5</value>
		<sim>MSFS</sim>
		<device>joystick</device>
	</models>
	<models>
		<setting>type</setting>
		<model>Experimental Mini-500.*</model>
		<value>Helicopter</value>
		<sim>MSFS</sim>
		<device>joystick</device>
		</models>
	<models>
		<setting>runway_rumble_intensity</setting>
		<model>F-14.*</model>
		<value>2.0</value>
		<sim>DCS</sim>
		<device>joystick</device>
		</models>
	<models>
		<setting>spoiler_buffet_intensity</setting>
		<model>F-14.*</model>
		<value>0.2</value>
		<sim>DCS</sim>
		<device>joystick</device>
		</models>
	<models>
		<setting>spoiler_motion_intensity</setting>
		<model>F-14.*</model>
		<value>0.0</value>
		<sim>DCS</sim>
		<device>joystick</device>
		</models>
	<models>
		<setting>type</setting>
		<model>F-14.*</model>
		<value>JetAircraft</value>
		<sim>DCS</sim>
		<device>joystick</device>
		</models>
	<models>
		<setting>type</setting>
		<model>F-15C</model>
		<value>JetAircraft</value>
		<sim>DCS</sim>
		<device>joystick</device>
		</models>
	<models>
		<setting>runway_rumble_intensity</setting>
		<model>F-15ESE</model>
		<value>3.0</value>
		<sim>DCS</sim>
		<device>joystick</device>
	</models>
	<models>
		<setting>type</setting>
		<model>F-15ESE</model>
		<value>JetAircraft</value>
		<sim>DCS</sim>
		<device>joystick</device>
	</models>
	<models>
		<setting>flaps_motion_intensity</setting>
		<model>F-16C_50</model>
		<value>0.0</value>
		<sim>DCS</sim>
		<device>joystick</device>
	</models>
	<models>
		<setting>runway_rumble_intensity</setting>
		<model>F-16C_50</model>
		<value>3.0</value>
		<sim>DCS</sim>
		<device>joystick</device>
	</models>
	<models>
		<setting>type</setting>
		<model>F-16C_50</model>
		<value>JetAircraft</value>
		<sim>DCS</sim>
		<device>joystick</device>
	</models>
	<models>
		<setting>runway_rumble_intensity</setting>
		<model>F-5E</model>
		<value>2.0</value>
		<sim>DCS</sim>
		<device>joystick</device>
	</models>
	<models>
		<setting>type</setting>
		<model>F-5E</model>
		<value>JetAircraft</value>
		<sim>DCS</sim>
		<device>joystick</device>
	</models>
	<models>
		<setting>aoa_reduction_max_force</setting>
		<model>FA-18C_hornet</model>
		<value>0.7</value>
		<sim>DCS</sim>
		<device>joystick</device>
		</models>
	<models>
		<setting>flaps_motion_intensity</setting>
		<model>FA-18C_hornet</model>
		<value>0.0</value>
		<sim>DCS</sim>
		<device>joystick</device>
		</models>
	<models>
		<setting>runway_rumble_intensity</setting>
		<model>FA-18C_hornet</model>
		<value>3.0</value>
		<sim>DCS</sim>
		<device>joystick</device>
	</models>
	<models>
		<setting>type</setting>
		<model>FA-18C_hornet</model>
		<value>JetAircraft</value>
		<sim>DCS</sim>
		<device>joystick</device>
		</models>
	<models>
		<setting>cyclic_spring_gain</setting>
		<model>FCP SA 342.*</model>
		<value>0.6</value>
		<sim>MSFS</sim>
		<device>joystick</device>
	</models>
	<models>
		<setting>etl_effect_intensity</setting>
		<model>FCP SA 342.*</model>
		<value>0.2</value>
		<sim>MSFS</sim>
		<device>joystick</device>
	</models>
	<models>
		<setting>etl_start_speed</setting>
		<model>FCP SA 342.*</model>
		<value>8</value>
		<unit>kt</unit>
		<sim>MSFS</sim>
		<device>joystick</device>
	</models>
	<models>
		<setting>etl_stop_speed</setting>
		<model>FCP SA 342.*</model>
		<value>16</value>
		<unit>kt</unit>
		<sim>MSFS</sim>
		<device>joystick</device>
	</models>
	<models>
		<setting>overspeed_shake_start</setting>
		<model>FCP SA 342.*</model>
		<value>45</value>
		<unit>m/s</unit>
		<sim>MSFS</sim>
		<device>joystick</device>
	</models>
	<models>
		<setting>rotor_blade_count</setting>
		<model>FCP SA 342.*</model>
		<value>3</value>
		<sim>MSFS</sim>
		<device>joystick</device>
	</models>
	<models>
		<setting>runway_rumble_intensity</setting>
		<model>FCP SA 342.*</model>
		<value>0.5</value>
		<sim>MSFS</sim>
		<device>joystick</device>
	</models>
	<models>
		<setting>type</setting>
		<model>FCP SA 342.*</model>
		<value>Helicopter</value>
		<sim>MSFS</sim>
		<device>joystick</device>
	</models>
	<models>
		<setting>type</setting>
		<model>FlightDesignCT Asobo</model>
		<value>PropellerAircraft</value>
		<sim>MSFS</sim>
		<device>joystick</device>
		</models>
	<models>
		<setting>etl_effect_intensity</setting>
		<model>FlyInside B206.*</model>
		<value>0.2</value>
		<sim>MSFS</sim>
		<device>joystick</device>
	</models>
	<models>
		<setting>etl_start_speed</setting>
		<model>FlyInside B206.*</model>
		<value>7</value>
		<unit>m/s</unit>
		<sim>MSFS</sim>
		<device>joystick</device>
	</models>
	<models>
		<setting>etl_stop_speed</setting>
		<model>FlyInside B206.*</model>
		<value>15</value>
		<unit>m/s</unit>
		<sim>MSFS</sim>
		<device>joystick</device>
	</models>
	<models>
		<setting>overspeed_shake_start</setting>
		<model>FlyInside B206.*</model>
		<value>45</value>
		<unit>m/s</unit>
		<sim>MSFS</sim>
		<device>joystick</device>
	</models>
	<models>
		<setting>rotor_blade_count</setting>
		<model>FlyInside B206.*</model>
		<value>2</value>
		<sim>MSFS</sim>
		<device>joystick</device>
	</models>
	<models>
		<setting>runway_rumble_intensity</setting>
		<model>FlyInside B206.*</model>
		<value>0.5</value>
		<sim>MSFS</sim>
		<device>joystick</device>
	</models>
	<models>
		<setting>type</setting>
		<model>FlyInside B206.*</model>
		<value>Helicopter</value>
		<sim>MSFS</sim>
		<device>joystick</device>
		</models>
	<models>
		<setting>etl_effect_intensity</setting>
		<model>FlyInside B47.*</model>
		<value>0.3</value>
		<sim>MSFS</sim>
		<device>joystick</device>
	</models>
	<models>
		<setting>etl_start_speed</setting>
		<model>FlyInside B47.*</model>
		<value>5</value>
		<unit>m/s</unit>
		<sim>MSFS</sim>
		<device>joystick</device>
	</models>
	<models>
		<setting>etl_stop_speed</setting>
		<model>FlyInside B47.*</model>
		<value>10</value>
		<unit>m/s</unit>
		<sim>MSFS</sim>
		<device>joystick</device>
	</models>
	<models>
		<setting>overspeed_shake_intensity</setting>
		<model>FlyInside B47.*</model>
		<value>0.3</value>
		<sim>DCS</sim>
		<device>joystick</device>
	</models>
	<models>
		<setting>overspeed_shake_start</setting>
		<model>FlyInside B47.*</model>
		<value>45</value>
		<unit>m/s</unit>
		<sim>MSFS</sim>
		<device>joystick</device>
	</models>
	<models>
		<setting>rotor_blade_count</setting>
		<model>FlyInside B47.*</model>
		<value>2</value>
		<sim>MSFS</sim>
		<device>joystick</device>
	</models>
	<models>
		<setting>runway_rumble_intensity</setting>
		<model>FlyInside B47.*</model>
		<value>0.5</value>
		<sim>MSFS</sim>
		<device>joystick</device>
	</models>
	<models>
		<setting>type</setting>
		<model>FlyInside B47.*</model>
		<value>Helicopter</value>
		<sim>MSFS</sim>
		<device>joystick</device>
	</models>
	<models>
		<setting>aileron_gain</setting>
		<model>Fox2 P42.*</model>
		<value>0.1</value>
		<sim>MSFS</sim>
		<device>joystick</device>
	</models>
	<models>
		<setting>joystick_trim_follow_gain_physical_x</setting>
		<model>Fox2 P42.*</model>
		<value>0.0</value>
		<sim>MSFS</sim>
		<device>joystick</device>
	</models>
	<models>
		<setting>joystick_trim_follow_gain_virtual_x</setting>
		<model>Fox2 P42.*</model>
		<value>0.0</value>
		<sim>MSFS</sim>
		<device>joystick</device>
	</models>
	<models>
		<setting>joystick_trim_follow_gain_virtual_y</setting>
		<model>Fox2 P42.*</model>
		<value>0.7</value>
		<sim>MSFS</sim>
		<device>joystick</device>
	</models>
	<models>
		<setting>type</setting>
		<model>Fox2 P42.*</model>
		<value>PropellerAircraft</value>
		<sim>MSFS</sim>
		<device>joystick</device>
		</models>
	<models>
		<setting>type</setting>
		<model>Fw 190.*</model>
		<value>PropellerAircraft</value>
		<sim>IL2</sim>
		<device>joystick</device>
		</models>
	<models>
		<setting>type</setting>
		<model>FW-190A8</model>
		<value>PropellerAircraft</value>
		<sim>DCS</sim>
		<device>joystick</device>
		</models>
	<models>
		<setting>buffeting_intensity</setting>
		<model>FW-190D9</model>
		<value>0.0</value>
		<sim>DCS</sim>
		<device>joystick</device>
	</models>
	<models>
		<setting>runway_rumble_intensity</setting>
		<model>FW-190D9</model>
		<value>1.0</value>
		<sim>DCS</sim>
		<device>joystick</device>
	</models>
	<models>
		<setting>type</setting>
		<model>FW-190D9</model>
		<value>PropellerAircraft</value>
		<sim>DCS</sim>
		<device>joystick</device>
		</models>
	<models>
		<setting>type</setting>
		<model>He 111.*</model>
		<value>PropellerAircraft</value>
		<sim>IL2</sim>
		<device>joystick</device>
		</models>
	<models>
		<setting>type</setting>
		<model>Hs 129 B-2</model>
		<value>PropellerAircraft</value>
		<sim>IL2</sim>
		<device>joystick</device>
		</models>
	<models>
		<setting>type</setting>
		<model>I-16</model>
		<value>PropellerAircraft</value>
		<sim>DCS</sim>
		<device>joystick</device>
		</models>
	<models>
		<setting>type</setting>
		<model>I-16 type 24</model>
		<value>PropellerAircraft</value>
		<sim>IL2</sim>
		<device>joystick</device>
		</models>
	<models>
		<setting>type</setting>
		<model>Il-2 mod.*</model>
		<value>PropellerAircraft</value>
		<sim>IL2</sim>
		<device>joystick</device>
		</models>
	<models>
		<setting>runway_rumble_intensity</setting>
		<model>JF-17</model>
		<value>2.0</value>
		<sim>DCS</sim>
		<device>joystick</device>
	</models>
	<models>
		<setting>type</setting>
		<model>JF-17</model>
		<value>JetAircraft</value>
		<sim>DCS</sim>
		<device>joystick</device>
	</models>
	<models>
		<setting>type</setting>
		<model>Ju 88 A-4</model>
		<value>PropellerAircraft</value>
		<sim>IL2</sim>
		<device>joystick</device>
		</models>
	<models>
		<setting>joystick_ap_following</setting>
		<model>Juice Goose.*</model>
		<value>false</value>
		<sim>MSFS</sim>
		<device>joystick</device>
		</models>
	<models>
		<setting>trim_following</setting>
		<model>Juice Goose.*</model>
		<value>false</value>
		<sim>MSFS</sim>
		<device>joystick</device>
	</models>
	<models>
		<setting>etl_start_speed</setting>
		<model>Ka-50</model>
		<value>6</value>
		<unit>m/s</unit>
		<sim>DCS</sim>
		<device>joystick</device>
		</models>
	<models>
		<setting>etl_stop_speed</setting>
		<model>Ka-50</model>
		<value>22</value>
		<unit>m/s</unit>
		<sim>DCS</sim>
		<device>joystick</device>
		</models>
	<models>
		<setting>overspeed_shake_start</setting>
		<model>Ka-50</model>
		<value>70</value>
		<unit>m/s</unit>
		<sim>DCS</sim>
		<device>joystick</device>
		</models>
	<models>
		<setting>type</setting>
		<model>Ka-50</model>
		<value>Helicopter</value>
		<sim>DCS</sim>
		<device>joystick</device>
		</models>
	<models>
		<setting>type</setting>
		<model>La-5 ser.8</model>
		<value>PropellerAircraft</value>
		<sim>IL2</sim>
		<device>joystick</device>
		</models>
	<models>
		<setting>type</setting>
		<model>LaGG-3 ser.29</model>
		<value>PropellerAircraft</value>
		<sim>IL2</sim>
		<device>joystick</device>
		</models>
	<models>
		<setting>runway_rumble_intensity</setting>
		<model>M-2000C</model>
		<value>2.0</value>
		<sim>DCS</sim>
		<device>joystick</device>
	</models>
	<models>
		<setting>type</setting>
		<model>M-2000C</model>
		<value>JetAircraft</value>
		<sim>DCS</sim>
		<device>joystick</device>
		</models>
	<models>
		<setting>type</setting>
		<model>MB-339.*</model>
		<value>JetAircraft</value>
		<sim>DCS</sim>
		<device>joystick</device>
	</models>
	<models>
		<setting>runway_rumble_intensity</setting>
		<model>MB-399.*</model>
		<value>2.0</value>
		<sim>DCS</sim>
		<device>joystick</device>
	</models>
	<models>
		<setting>type</setting>
		<model>MC.202 ser.VIII</model>
		<value>PropellerAircraft</value>
		<sim>IL2</sim>
		<device>joystick</device>
		</models>
	<models>
		<setting>type</setting>
		<model>Me 262 A</model>
		<value>JetAircraft</value>
		<sim>IL2</sim>
		<device>joystick</device>
		</models>
	<models>
		<setting>type</setting>
		<model>Mi-24P</model>
		<value>Helicopter</value>
		<sim>DCS</sim>
		<device>joystick</device>
		</models>
	<models>
		<setting>type</setting>
		<model>Mi-8MT</model>
		<value>Helicopter</value>
		<sim>DCS</sim>
		<device>joystick</device>
		</models>
	<models>
		<setting>type</setting>
		<model>MiG-15.*</model>
		<value>JetAircraft</value>
		<sim>DCS</sim>
		<device>joystick</device>
	</models>
	<models>
		<setting>trim_workaround</setting>
		<model>MiG-19.*</model>
		<value>true</value>
		<sim>DCS</sim>
		<device>joystick</device>
	</models>
	<models>
		<setting>type</setting>
		<model>MiG-19.*</model>
		<value>JetAircraft</value>
		<sim>DCS</sim>
		<device>joystick</device>
		</models>
	<models>
		<setting>buffet_aoa</setting>
		<model>MiG-21.*</model>
		<value>8</value>
		<sim>DCS</sim>
		<device>joystick</device>
		</models>
	<models>
		<setting>buffeting_intensity</setting>
		<model>MiG-21.*</model>
		<value>0.25</value>
		<sim>DCS</sim>
		<device>joystick</device>
		</models>
	<models>
		<setting>type</setting>
		<model>MiG-21.*</model>
		<value>JetAircraft</value>
		<sim>DCS</sim>
		<device>joystick</device>
		</models>
	<models>
		<setting>type</setting>
		<model>MiG-29.*</model>
		<value>JetAircraft</value>
		<sim>DCS</sim>
		<device>joystick</device>
		</models>
	<models>
		<setting>type</setting>
		<model>MiG-3 ser.24</model>
		<value>PropellerAircraft</value>
		<sim>IL2</sim>
		<device>joystick</device>
		</models>
	<models>
		<setting>runway_rumble_intensity</setting>
		<model>Mirage-F1.*</model>
		<value>2.0</value>
		<sim>DCS</sim>
		<device>joystick</device>
	</models>
	<models>
		<setting>type</setting>
		<model>Mirage-F1.*</model>
		<value>JetAircraft</value>
		<sim>DCS</sim>
		<device>joystick</device>
		</models>
	<models>
		<setting>type</setting>
		<model>MosquitoFBMkVI</model>
		<value>PropellerAircraft</value>
		<sim>DCS</sim>
		<device>joystick</device>
		</models>
	<models>
		<setting>type</setting>
		<model>P-38J-25</model>
		<value>PropellerAircraft</value>
		<sim>IL2</sim>
		<device>joystick</device>
		</models>
	<models>
		<setting>type</setting>
		<model>P-39L-1</model>
		<value>PropellerAircraft</value>
		<sim>IL2</sim>
		<device>joystick</device>
		</models>
	<models>
		<setting>type</setting>
		<model>P-40E-1</model>
		<value>PropellerAircraft</value>
		<sim>IL2</sim>
		<device>joystick</device>
		</models>
	<models>
		<setting>type</setting>
		<model>P-47D.*</model>
		<value>PropellerAircraft</value>
		<sim>DCS</sim>
		<device>joystick</device>
	</models>
	<models>
		<setting>type</setting>
		<model>P-47D-28</model>
		<value>PropellerAircraft</value>
		<sim>IL2</sim>
		<device>joystick</device>
		</models>
	<models>
		<setting>buffeting_intensity</setting>
		<model>P-51D</model>
		<value>0.0</value>
		<sim>DCS</sim>
		<device>joystick</device>
		</models>
	<models>
		<setting>runway_rumble_intensity</setting>
		<model>P-51D</model>
		<value>1.0</value>
		<sim>DCS</sim>
		<device>joystick</device>
		</models>
	<models>
		<setting>type</setting>
		<model>P-51D</model>
		<value>PropellerAircraft</value>
		<sim>DCS</sim>
		<device>joystick</device>
		</models>
	<models>
		<setting>type</setting>
		<model>P-51D-15</model>
		<value>PropellerAircraft</value>
		<sim>IL2</sim>
		<device>joystick</device>
		</models>
	<models>
		<setting>type</setting>
		<model>Pe-2 ser.*</model>
		<value>PropellerAircraft</value>
		<sim>IL2</sim>
		<device>joystick</device>
		</models>
	<models>
		<setting>joystick_trim_follow_gain_virtual_y</setting>
		<model>pesim-maule-m7235.*</model>
		<value>-0.05</value>
		<sim>MSFS</sim>
		<device>joystick</device>
	</models>
	<models>
		<setting>type</setting>
		<model>pesim-maule-m7235.*</model>
		<value>PropellerAircraft</value>
		<sim>MSFS</sim>
		<device>joystick</device>
		</models>
	<models>
		<setting>elevator_droop_moment</setting>
		<model>Pilatus PC-6*</model>
		<value>0.3</value>
		<sim>MSFS</sim>
		<device>joystick</device>
	</models>
	<models>
		<setting>joystick_trim_follow_gain_virtual_y</setting>
		<model>Pilatus PC-6*</model>
		<value>0.65</value>
		<sim>MSFS</sim>
		<device>joystick</device>
	</models>
	<models>
		<setting>type</setting>
		<model>Pilatus PC-6*</model>
		<value>TurbopropAircraft</value>
		<sim>MSFS</sim>
		<device>joystick</device>
	</models>
	<models>
		<setting>aileron_gain</setting>
		<model>Pitts Asobo*</model>
		<value>0.04</value>
		<sim>MSFS</sim>
		<device>joystick</device>
	</models>
	<models>
		<setting>elevator_droop_moment</setting>
		<model>Pitts Asobo*</model>
		<value>0.3</value>
		<sim>MSFS</sim>
		<device>joystick</device>
	</models>
	<models>
		<setting>joystick_trim_follow_gain_virtual_y</setting>
		<model>Pitts Asobo*</model>
		<value>0.1</value>
		<sim>MSFS</sim>
		<device>joystick</device>
	</models>
	<models>
		<setting>joystick_x_axis_scale</setting>
		<model>Pitts Asobo*</model>
		<value>0.6</value>
		<sim>MSFS</sim>
		<device>joystick</device>
		</models>
	<models>
		<setting>type</setting>
		<model>Pitts Asobo*</model>
		<value>PropellerAircraft</value>
		<sim>MSFS</sim>
		<device>joystick</device>
		</models>
	<models>
		<setting>etl_effect_intensity</setting>
		<model>Robinson R44.*</model>
		<value>0.2</value>
		<sim>MSFS</sim>
		<device>joystick</device>
	</models>
	<models>
		<setting>etl_start_speed</setting>
		<model>Robinson R44.*</model>
		<value>7</value>
		<unit>m/s</unit>
		<sim>MSFS</sim>
		<device>joystick</device>
	</models>
	<models>
		<setting>etl_stop_speed</setting>
		<model>Robinson R44.*</model>
		<value>15</value>
		<unit>m/s</unit>
		<sim>MSFS</sim>
		<device>joystick</device>
	</models>
	<models>
		<setting>joystick_x_axis_scale</setting>
		<model>Robinson R44.*</model>
		<value>0.85</value>
		<sim>MSFS</sim>
		<device>joystick</device>
	</models>
	<models>
		<setting>joystick_y_axis_scale</setting>
		<model>Robinson R44.*</model>
		<value>0.85</value>
		<sim>MSFS</sim>
		<device>joystick</device>
	</models>
	<models>
		<setting>rotor_blade_count</setting>
		<model>Robinson R44.*</model>
		<value>2</value>
		<sim>MSFS</sim>
		<device>joystick</device>
	</models>
	<models>
		<setting>runway_rumble_intensity</setting>
		<model>Robinson R44.*</model>
		<value>0.5</value>
		<sim>MSFS</sim>
		<device>joystick</device>
	</models>
	<models>
		<setting>type</setting>
		<model>Robinson R44.*</model>
		<value>Helicopter</value>
		<sim>MSFS</sim>
		<device>joystick</device>
		</models>
	<models>
		<setting>cm_vibration_intensity</setting>
		<model>SA342.*</model>
		<value>0.15</value>
		<sim>DCS</sim>
		<device>joystick</device>
		</models>
	<models>
		<setting>etl_effect_intensity</setting>
		<model>SA342.*</model>
		<value>0.3</value>
		<sim>DCS</sim>
		<device>joystick</device>
	</models>
	<models>
		<setting>etl_start_speed</setting>
		<model>SA342.*</model>
		<value>6</value>
		<unit>m/s</unit>
		<sim>DCS</sim>
		<device>joystick</device>
	</models>
	<models>
		<setting>etl_stop_speed</setting>
		<model>SA342.*</model>
		<value>22</value>
		<unit>m/s</unit>
		<sim>DCS</sim>
		<device>joystick</device>
	</models>
	<models>
		<setting>overspeed_shake_intensity</setting>
		<model>SA342.*</model>
		<value>0.25</value>
		<sim>DCS</sim>
		<device>joystick</device>
		</models>
	<models>
		<setting>overspeed_shake_start</setting>
		<model>SA342.*</model>
		<value>75</value>
		<unit>m/s</unit>
		<sim>DCS</sim>
		<device>joystick</device>
	</models>
	<models>
		<setting>type</setting>
		<model>SA342.*</model>
		<value>Helicopter</value>
		<sim>DCS</sim>
		<device>joystick</device>
		</models>
	<models>
		<setting>weapon_release_intensity</setting>
		<model>SA342.*</model>
		<value>0.12</value>
		<sim>DCS</sim>
		<device>joystick</device>
		</models>
	<models>
		<setting>type</setting>
		<model>Savage Grravel.*</model>
		<value>PropellerAircraft</value>
		<sim>MSFS</sim>
		<device>joystick</device>
		</models>
	<models>
		<setting>etl_effect_intensity</setting>
		<model>Shrike.*</model>
		<value>0.4</value>
		<sim>MSFS</sim>
		<device>joystick</device>
	</models>
	<models>
		<setting>etl_start_speed</setting>
		<model>Shrike.*</model>
		<value>10</value>
		<unit>kt</unit>
		<sim>MSFS</sim>
		<device>joystick</device>
	</models>
	<models>
		<setting>etl_stop_speed</setting>
		<model>Shrike.*</model>
		<value>30</value>
		<unit>kt</unit>
		<sim>MSFS</sim>
		<device>joystick</device>
	</models>
	<models>
		<setting>overspeed_shake_intensity</setting>
		<model>Shrike.*</model>
		<value>0.3</value>
		<sim>DCS</sim>
		<device>joystick</device>
	</models>
	<models>
		<setting>overspeed_shake_start</setting>
		<model>Shrike.*</model>
		<value>130</value>
		<unit>kt</unit>
		<sim>MSFS</sim>
		<device>joystick</device>
	</models>
	<models>
		<setting>rotor_blade_count</setting>
		<model>Shrike.*</model>
		<value>5</value>
		<sim>MSFS</sim>
		<device>joystick</device>
	</models>
	<models>
		<setting>runway_rumble_intensity</setting>
		<model>Shrike.*</model>
		<value>0.6</value>
		<sim>MSFS</sim>
		<device>joystick</device>
	</models>
	<models>
		<setting>type</setting>
		<model>Shrike.*</model>
		<value>Helicopter</value>
		<sim>MSFS</sim>
		<device>joystick</device>
	</models>
	<models>
		<setting>type</setting>
		<model>Spitfire Mk.*</model>
		<value>PropellerAircraft</value>
		<sim>IL2</sim>
		<device>joystick</device>
		</models>
	<models>
		<setting>buffet_aoa</setting>
		<model>SpitfireLFMkIX</model>
		<value>12</value>
		<sim>DCS</sim>
		<device>joystick</device>
		</models>
	<models>
		<setting>stall_aoa</setting>
		<model>SpitfireLFMkIX</model>
		<value>16</value>
		<sim>DCS</sim>
		<device>joystick</device>
		</models>
	<models>
		<setting>type</setting>
		<model>SpitfireLFMkIX</model>
		<value>PropellerAircraft</value>
		<sim>DCS</sim>
		<device>joystick</device>
	</models>
	<models>
		<setting>buffeting_intensity</setting>
		<model>Su-25.*</model>
		<value>0.0</value>
		<sim>DCS</sim>
		<device>joystick</device>
		</models>
	<models>
		<setting>type</setting>
		<model>Su-25.*</model>
		<value>JetAircraft</value>
		<sim>DCS</sim>
		<device>joystick</device>
		</models>
	<models>
		<setting>type</setting>
		<model>Su-27.*</model>
		<value>JetAircraft</value>
		<sim>DCS</sim>
		<device>joystick</device>
		</models>
	<models>
		<setting>runway_rumble_intensity</setting>
		<model>Su-33</model>
		<value>2.0</value>
		<sim>DCS</sim>
		<device>joystick</device>
	</models>
	<models>
		<setting>type</setting>
		<model>Su-33</model>
		<value>JetAircraft</value>
		<sim>DCS</sim>
		<device>joystick</device>
		</models>
	<models>
		<setting>spoiler_buffet_intensity</setting>
		<model>TBM 930 Asobo</model>
		<value>0.0</value>
		<sim>MSFS</sim>
		<device>joystick</device>
	</models>
	<models>
		<setting>spoiler_motion_intensity</setting>
		<model>TBM 930 Asobo</model>
		<value>0.0</value>
		<sim>MSFS</sim>
		<device>joystick</device>
	</models>
	<models>
		<setting>type</setting>
		<model>TBM 930 Asobo</model>
		<value>TurbopropAircraft</value>
		<sim>MSFS</sim>
		<device>joystick</device>
		</models>
	<models>
		<setting>type</setting>
		<model>Tempest Mk.V ser.2</model>
		<value>PropellerAircraft</value>
		<sim>IL2</sim>
		<device>joystick</device>
		</models>
	<models>
		<setting>buffeting_intensity</setting>
		<model>TF-51D</model>
		<value>0.0</value>
		<sim>DCS</sim>
		<device>joystick</device>
		</models>
	<models>
		<setting>gear_buffet_intensity</setting>
		<model>TF-51D</model>
		<value>0.15</value>
		<sim>DCS</sim>
		<device>joystick</device>
	</models>
	<models>
		<setting>inertia_force</setting>
		<model>TF-51D</model>
		<value>0.2</value>
		<sim>DCS</sim>
		<device>joystick</device>
		</models>
	<models>
		<setting>rpm_scale</setting>
		<model>TF-51D</model>
		<value>31.5</value>
		<sim>DCS</sim>
		<device>joystick</device>
		</models>
	<models>
		<setting>runway_rumble_intensity</setting>
		<model>TF-51D</model>
		<value>1.0</value>
		<sim>DCS</sim>
		<device>joystick</device>
		</models>

	<models>
	<setting>type</setting>
	<model>TF-51D</model>
	<value>PropellerAircraft</value>
	<sim>DCS</sim>
	<device>joystick</device>
	</models>
	<models>
		<setting>cm_vibration_intensity</setting>
		<model>UH-1H</model>
		<value>0.12</value>
		<sim>DCS</sim>
		<device>joystick</device>
	</models>
	<models>
		<setting>etl_effect_intensity</setting>
		<model>UH-1H</model>
		<value>0.25</value>
		<sim>DCS</sim>
		<device>joystick</device>
	</models>
	<models>
		<setting>etl_start_speed</setting>
		<model>UH-1H</model>
		<value>10</value>
		<unit>m/s</unit>
		<sim>DCS</sim>
		<device>joystick</device>
	</models>
	<models>
		<setting>etl_stop_speed</setting>
		<model>UH-1H</model>
		<value>20</value>
		<unit>m/s</unit>
		<sim>DCS</sim>
		<device>joystick</device>
	</models>
	<models>
		<setting>gun_vibration_intensity</setting>
		<model>UH-1H</model>
		<value>0.1</value>
		<sim>DCS</sim>
		<device>joystick</device>
	</models>
	<models>
		<setting>overspeed_shake_intensity</setting>
		<model>UH-1H</model>
		<value>0.2</value>
		<sim>DCS</sim>
		<device>joystick</device>
	</models>
	<models>
		<setting>overspeed_shake_start</setting>
		<model>UH-1H</model>
		<value>60</value>
		<unit>m/s</unit>
		<sim>DCS</sim>
		<device>joystick</device>
	</models>
	<models>
		<setting>type</setting>
		<model>UH-1H</model>
		<value>Helicopter</value>
		<sim>DCS</sim>
		<device>joystick</device>
		</models>
	<models>
		<setting>weapon_release_intensity</setting>
		<model>UH-1H</model>
		<value>0.2</value>
		<sim>DCS</sim>
		<device>joystick</device>
	</models>
	<models>
		<setting>cm_vibration_intensity</setting>
		<model>UH-60L</model>
		<value>0.12</value>
		<sim>DCS</sim>
		<device>joystick</device>
	</models>
	<models>
		<setting>etl_effect_intensity</setting>
		<model>UH-60L</model>
		<value>0.25</value>
		<sim>DCS</sim>
		<device>joystick</device>
	</models>
	<models>
		<setting>etl_stop_speed</setting>
		<model>UH-60L</model>
		<value>20</value>
		<unit>m/s</unit>
		<sim>DCS</sim>
		<device>joystick</device>
	</models>
	<models>
		<setting>gun_vibration_intensity</setting>
		<model>UH-60L</model>
		<value>0.1</value>
		<unit></unit>
		<sim>DCS</sim>
		<device>joystick</device>
	</models>
	<models>
		<setting>type</setting>
		<model>UH-60L</model>
		<value>Helicopter</value>
		<sim>DCS</sim>
		<device>joystick</device>
		</models>
	<models>
		<setting>weapon_release_intensity</setting>
		<model>UH-60L</model>
		<value>0.12</value>
		<sim>DCS</sim>
		<device>joystick</device>
	</models>
	<models>
		<setting>aileron_gain</setting>
		<model>Vertigo.*</model>
		<value>0.1</value>
		<sim>MSFS</sim>
		<device>joystick</device>
	</models>
	<models>
		<setting>type</setting>
		<model>Vertigo.*</model>
		<value>TurbopropAircraft</value>
		<sim>MSFS</sim>
		<device>joystick</device>
		</models>
	<models>
		<setting>joystick_trim_follow_gain_virtual_y</setting>
		<model>Wilga.*</model>
		<value>0.45</value>
		<sim>MSFS</sim>
		<device>joystick</device>
	</models>
	<models>
		<setting>type</setting>
		<model>Wilga.*</model>
		<value>PropellerAircraft</value>
		<sim>MSFS</sim>
		<device>joystick</device>
		</models>
	<models>
		<setting>joystick_trim_follow_gain_virtual_y</setting>
		<model>XCub.*</model>
		<value>0.6</value>
		<sim>MSFS</sim>
		<device>joystick</device>
		</models>
	<models>
		<setting>type</setting>
		<model>XCub.*</model>
		<value>PropellerAircraft</value>
		<sim>MSFS</sim>
		<device>joystick</device>
		</models>
	<models>
		<setting>type</setting>
		<model>Yak-1 ser.69</model>
		<value>PropellerAircraft</value>
		<sim>IL2</sim>
		<device>joystick</device>
		</models>
	<models>
		<setting>type</setting>
		<model>Yak-7B series 36</model>
		<value>PropellerAircraft</value>
		<sim>IL2</sim>
		<device>joystick</device>
		</models>
</TelemFFB>